{
  "page_2.png-底部文本框有头像非战斗": "ARE You READY, DARLINGS? # HERE, LIVE AT HOTLAND' $ PREMIERE DoJo.",
  "page_3.png-底部文本框有头像非战斗": "WE' RE ABOUT TO MAKE HISTORYttt",
  "page_4.png-底部文本框有头像非战斗": "HERE, THE UNDERGROUND' $ BRAVEST, TOUGHEST, AHD Most DAZZLING FIGHTERS",
  "page_5.png-底部文本框有头像非战斗": "HAVE GATHERED FOR THE CHANCE TO BATTLE THEIR WAY To STARDOMG",
  "page_6.png-底部文本框有头像非战斗": "YES, STARDOMI OR RATHER, cO-STARDOM; In MY UPCOMING SUMMER FLICK.",
  "page_7.png-底部文本框有头像非战斗": "METTATOH THE MOVIE XXVIII: STARS COLLIDE!",
  "page_8.png-底部文本框有头像非战斗": "WAIT, REALLY-l?",
  "page_9.png-底部文本框有头像非战斗": "WhY YES ! EVEN Yov COULD RISE ABOVE THE REST!",
  "page_10.png-底部文本框有头像非战斗": "You MIGHT EVEH BECOME THE NEW FACE In ENTERTAIHMENT.",
  "page_11.png-底部文本框有头像非战斗": "WELL, hOt REALLY. # BUT A CLOSE SECOND ISN' T HALF -",
  "page_12.png-底部文本框有头像非战斗": "Will you to the point already?! get",
  "page_13.png-底部文本框有头像非战斗": "ALWAYS A SPOILSPORT, EH? # BUT FINE. IF You SIMPLY MuST   RUSH THIS ALONG.",
  "page_14.png-底部文本框有头像非战斗": "WE CAN' T FORGET OUR  VIP COMPETITOR, THE OHE AHD ONLY HUMAM  MENACE!",
  "page_16.png-顶部文本框有头像非战斗": "S0, I take it we have no say in this.",
  "page_17.png-底部文本框有头像非战斗": "Of course not. Besides, you wouldn' t Wanna rob them of a show, right?",
  "page_18.png-底部文本框有头像非战斗": "Everyone came all this Way to see curbstomped? get you",
  "page_19.png-底部文本框有头像非战斗": "AND FOR OUR COMPETITORS, THE RARE  CHANCE To FACE A HUMAN  IM COMBATt",
  "page_20.png-底部文本框无头像非战斗": "Dude this is gonna be AWESOME ! I' ve NEVER seen a human fight beforet",
  "page_21.png-底部文本框有头像非战斗": "AND THAT' $ hOT ALLI IF You BET HOW, Yov' LL HAVE A CHANCE TO WIM:",
  "page_22.png-底部文本框有头像非战斗": "A CANDLELIT DINNER. WITH MY DEAR COUSIH BLOOKYI",
  "page_23.png-底部文本框有头像非战斗": "W- Wait, what?t",
  "page_24.png-底部文本框有头像非战斗": "COME OH , BLOOKY: I THINK Yov' RE DUE FOR A LITTLE TIME In THE SPOTLIGHT.",
  "page_25.png-底部文本框有头像非战斗": "but me ttaton.",
  "page_26.png-底部文本框有头像非战斗": "0H, ALL RIGHT. WE' LL MAKE It AN   AUTOGRAPH SESSIOM FOR You.",
  "page_27.png-底部文本框有头像非战斗": "AND A DATE WITH UMDYNE INSTEAD#",
  "page_28.png-底部文本框有头像非战斗": "WHAT?# Are seriously SOLICITInG ME?! you",
  "page_29.png-底部文本框有头像非战斗": "nO, I JuST LOVE SEEING YOuR REACTIONS. THE DATE' $ WITH ME.",
  "page_30.png-顶部文本框有头像非战斗": "In that case, I bet 200g on Papyrus.",
  "page_31.png-顶部文本框有头像非战斗": "R-REALLY-! WELL, IN THAT CASE LL BET ioooG ON You FRISK!",
  "page_32.png-底部文本框有头像非战斗": "Papyrus.",
  "page_33.png-底部文本框无头像非战斗": "Oh my god, Bratty: Like, this is some tough competition:",
  "page_34.png-底部文本框无头像非战斗": "Soooo, who are YOu gonna bet on?",
  "page_35.png-底部文本框无头像非战斗": "# I dunno. I mean, the kid DI make it through the guard AND Mettaton.",
  "page_36.png-底部文本框无头像非战斗": "Hot to mention Alphys.",
  "page_37.png-底部文本框有头像非战斗": "I knowt Let' $, like, lly bet at the last minute.",
  "page_38.png-底部文本框无头像非战斗": "Catty, I like the way you think:",
  "page_39.png-底部文本框有头像非战斗": "WELL, I SEE HO REASON TO DELAY ANY FURTHER# LET' $ WELCONE OuR COMPETITORS",
  "page_41.png-底部文本框有头像非战斗": "AND I' D LIKE TO THANK ouR GENEROUS SPONSOR: A dog.",
  "page_42.png-底部文本框有头像非战斗": "AFTER ALL, HIS SHRINE REALLY ADDs TO THE TAckY ANIME ATMOSPHEREt",
  "page_43.png-顶部文本框有头像非战斗": "I have 50 many questions.",
  "page_44.png-顶部文本框有头像非战斗": "FRISK, IF THERE'S ONE THING You SHOULD KNOW",
  "page_45.png-顶部文本框有头像非战斗": "IT's THAT THERE 15 NO LoGic ONLY DOG;",
  "page_46.png-底部文本框有头像非战斗": "enough chattert It' $ GAME time punk, s0 butt up heret Okay, get your",
  "page_47.png-顶部文本框有头像非战斗": "Pff; mon, Papyrus. How bout We make this a team? tag",
  "page_48.png-顶部文本框有头像非战斗": "WOULDN'T HAVE IT ANY OTHER WAYW",
  "page_49.png-底部文本框有头像非战斗": "HOW TOUCHING? BUT WILL THE  POWER OF TEAMWORK BE EhOUGH TO -",
  "page_50.png-底部文本框无头像非战斗": "That' $ it, that' $ it, THAT' $ It  :",
  "page_51.png-底部文本框无头像非战斗": "# I' ve waited long enough? # Al1 this fanfare means HOTHING ! # It' $ just a WASTE OF TIMETT!",
  "page_52.png-底部文本框无头像非战斗": "These people want a FIGHT, and I' m here for SWEET REVENGE?",
  "page_53.png-底部文本框有头像非战斗": "human, prepare yourself! use THIS TIME, no one 1s 9 to interferet",
  "page_54.png-战斗文本框无头像战斗": "Mad Dummy challenges you!",
  "page_55.png-战斗文本框无头像战斗": "Mad Dummy",
  "page_56.png-战斗文本框无头像战斗": "Check Talk",
  "page_57.png-战斗文本框无头像战斗": "MAD DUMMY ATK 45 DEF YES # A ghost this angry should NEVER possess advanced weaponry:",
  "page_58.png-战斗文本框无头像战斗": "GEEZ, CANT BELIEVE IT'S STILL UPSET! GUESS YELL HAVE TO TREAD CAREFULLY",
  "page_59.png-战斗文本框无头像战斗": "BLUE ATTACK ~B_ DARRIER D BARRAGE CONCOCTEREST",
  "page_76.png-战斗文本框无头像战斗": "Revenge of Jerry:",
  "page_77.png-战斗文本框无头像战斗": "Check Ditch Yell",
  "page_78.png-战斗文本框无头像战斗": "You insults at Jerry; but it doesn' t bat an eye. ye11",
  "page_80.png-战斗文本框无头像战斗": "OH NOW JERRY'5 GOING To TANK THE RATINGSI YE HAVE TO DO SOMETHING FAST!",
  "page_81.png-战斗文本框无头像战斗": "CHECK IMFROVISE",
  "page_82.png-战斗文本框无头像战斗": "WAVE MY ARMS TRYING To THRUST JERRY OUT OF THE RINGW",
  "page_83.png-战斗文本框无头像战斗": "THEN REMEMBER FM NOT SANS CURSESW",
  "page_86.png-战斗文本框无头像战斗": "The crowd is booing: And you are, too.",
  "page_87.png-战斗文本框无头像战斗": "You to ditch, but then you remember that this is a tournament. try",
  "page_88.png-战斗文本框无头像战斗": "Losing to Jerry is unacceptable",
  "page_89.png-战斗文本框无头像战斗": "AGH, COME ONW! THERE MuSt BE A BETTER SOLUTION!",
  "page_90.png-战斗文本框无头像战斗": "MAKE BONES BURST FROM BENEATH JERRY'5 FEETW",
  "page_91.png-战斗文本框无头像战斗": "But IT BLOCK5 THEM WITH ITS BEEFY ARMS! CURSE You, BICEFSW",
  "page_102.png-战斗文本框无头像战斗": "Glyde swoops in!",
  "page_103.png-战斗文本框无头像战斗": "Check Applaud Boo Do Hothing",
  "page_104.png-战斗文本框无头像战斗": "GLYDE Refuses to give stats_ Seems it' $ a bit of a tryhard.",
  "page_105.png-战斗文本框无头像战斗": "OH NOW Just LOOK AT THAT HAIR! FLL HAVE To DRING MY A-GAMEWW",
  "page_106.png-战斗文本框无头像战斗": "CHECK DISTRACT SHOY OFF BOo",
  "page_107.png-战斗文本框无头像战斗": "FROUDLY SHOY OFF MY BIGGEST BONES, TWIRLING THEM AND STRIKING A FOSE!",
  "page_108.png-战斗文本框无头像战斗": "But GLYDE Just ROLLS ITS EYES NOOO!",
  "page_111.png-战斗文本框无头像战斗": "Glyde winks at the audience_ Bratty and Catty swoon, while Undyne just glares",
  "page_112.png-战斗文本框无头像战斗": "Check Applaud Boo Do Hothing",
  "page_113.png-战斗文本框无头像战斗": "You tell Glyde that its pompadour is tacky; but haters just make it stronger",
  "page_114.png-战斗文本框无头像战斗": "ATK up, DEF down #",
  "page_115.png-战斗文本框无头像战斗": "DANG IT! THERE MuSt BE SOME YAY To DEFLATE THAT BLOATED EGO!",
  "page_116.png-战斗文本框无头像战斗": "BLUE ATTACK 6 DARRIER D BARRAGE CONCOCTEREST",
  "page_120.png-战斗文本框无头像战斗": "Glyde kisses its own photograph before throwing it to the crowd.",
  "page_121.png-战斗文本框无头像战斗": "You Clap Slowly: Glyde puffs out its chest with pride.",
  "page_122.png-战斗文本框无头像战斗": "OH, COME ON, FRISK! THOUGHT You YERE ON MY SIDEWW",
  "page_123.png-战斗文本框无头像战斗": "OFFER GLYDE A BOOK OF SuDOku IT LOOKS BEWILDERED",
  "page_124.png-战斗文本框无头像战斗": "ITS ACCURACY DROFS THIS TURN!",
  "page_127.png-战斗文本框无头像战斗": "Glyde is still failing at puzzles and at life.",
  "page_128.png-战斗文本框无头像战斗": "You clap even slower, but Glyde grins anyway: Talk about dense",
  "page_129.png-战斗文本框无头像战斗": "HMM THIS MIGHT BE A GOOD TIME To LAUNCH A COUNTERSTRIKE!",
  "page_130.png-战斗文本框无头像战斗": "CHECK DISTRACT SHOY OFF IGNORE",
  "page_131.png-战斗文本框无头像战斗": "FRETEND GLYDE ISNT THERE IT STARTS To FOUT, Just A5 FLANNEDW",
  "page_133.png-战斗文本框无头像战斗": "Glyde looks to Papyrus and then gives itself a high five. It' $ not fooling anyone_",
  "page_134.png-战斗文本框无头像战斗": "# You do nothing: Glyde begins to sweat.",
  "page_135.png-战斗文本框无头像战斗": "NYEH HEH HEH! THIS 15 FERFECT ! NOw, LET'5 TURN TIS AROUNDW",
  "page_136.png-战斗文本框无头像战斗": "BEGIN JUGGLING MY BONESI THE CROwD CHEERS YILDLY!",
  "page_138.png-战斗文本框无头像战斗": "Glyde starts shouting \"cool\" Words like radtastical, but nobody cares.",
  "page_139.png-战斗文本框无头像战斗": "# You ate the Unisicle_ HP  maxed out.",
  "page_140.png-战斗文本框无头像战斗": "HOw THE TABLES HAVE TURNEDW",
  "page_141.png-战斗文本框无头像战斗": "REMOVE MY HOvER BOARD FROM MY DIMENSIONAL STORAGE!",
  "page_142.png-战斗文本框无头像战斗": "EvERYONE GASPs IN UTTER AMAZEMENT !",
  "page_155.png-战斗文本框无头像战斗": "Sorry stumbles on stage_ S0",
  "page_156.png-战斗文本框无头像战斗": "Check Something",
  "page_157.png-战斗文本框无头像战斗": "s0  SORY # This creature is definitely out of his element.",
  "page_158.png-战斗文本框无头像战斗": "WOWIE THIS FOOR DRAGON LOOKS AwFULLY ANXIOuS",
  "page_159.png-战斗文本框无头像战斗": "CHECK ENCOURAGE DISTRACT",
  "page_160.png-战斗文本框无头像战斗": "FEAR NOT, FRIEND! THOUGH YERE ENEMIES, FM SURE YOULL WOw THE CROWDSW",
  "page_165.png-战斗文本框无头像战斗": "Sorry shuffles anxiously: S0",
  "page_166.png-战斗文本框无头像战斗": "You Wave, but he just ducks his head;",
  "page_167.png-战斗文本框无头像战斗": "STILL NOTHING? YELL, THAT WON'T DOW",
  "page_168.png-战斗文本框无头像战斗": "THAT WAS A GOOD START, But FM SURE You CAN DO EvEN BETTERW!",
  "page_169.png-战斗文本框无头像战斗": "AFTER ALL, EvERY MONSTER HAS SOMETHING QUIRKY AND UNIQUE ABOUT THEMW",
  "page_177.png-战斗文本框无头像战斗": "Insert obligatory remark about science here.",
  "page_178.png-战斗文本框无头像战斗": "Check Compliment Steal",
  "page_179.png-战斗文本框无头像战斗": "Yov compliment S0 Sorry' $ creativity: He blushes. ATK downt",
  "page_180.png-战斗文本框无头像战斗": "THERE YE GO! NO YE CAN HAVE A FAIR MATCHW!!",
  "page_181.png-战斗文本框无头像战斗": "BLUE ATTACK 6 DARRIER 01 BARRAGE CONCOCTEREST",
  "page_186.png-战斗文本框无头像战斗": "Does this count as creating life? Who even MADE that tablet?",
  "page_187.png-战斗文本框无头像战斗": "You to grab the tablet, but So Sorry' $ watching you/ DEF up! try",
  "page_188.png-战斗文本框无头像战斗": "HMM WAIT! THIS GIVES ME AN IDEA!",
  "page_189.png-战斗文本框无头像战斗": "CHECK ENCOURAGE DISTRACT",
  "page_190.png-战斗文本框无头像战斗": "FROCEED To MAKE A DRAMING OF MY OWN",
  "page_191.png-战斗文本框无头像战斗": "COMFLETE WITH SwELLING MuSCLES AND LONG, FLOWING HAIRW!",
  "page_195.png-战斗文本框无头像战斗": "The power of creation is the palm of your hands ! in",
  "page_196.png-战斗文本框无头像战斗": "Check Compliment Steal Draw",
  "page_197.png-战斗文本框无头像战斗": "You draw a giant fan. Suddenly:",
  "page_211.png-战斗文本框无头像战斗": "Talk about forceful_"
}