{
    "Event-level2-4045-Array-1": "@0.05f%redf * 你最好去检查下电梯。",
    "Event-level2-4067-Array-1": "* 石头后面有一台\n  损坏的摄像头。",
    "Event-level2-4441-Array-1": "* 这盏灯已经风光不再了。",
    "Event-level2-4441-Array-2": "%redf@0.05f* 这是一盏坏了的灯。",
    "Event-level2-4832-Array-1": "@0.05f%redf * 他还忙着屠戮其他怪物呢！",
    "Event-level2-4832-Array-2": "@0.05f%redf * 趁早干掉Mettaton！",
    "Event-level2-4832-Array-3": "@0.05f%redf * 继续前进吧。",
    "Event-level2-4839-Array-1": "@0.05f%redf * 真是撞八辈子福了。",
    "Event-level2-4839-Array-2": "@0.05f%redf * 电梯竟然能用。",
    "Event-level2-4846-Array-1": "* 灌木丛中藏着一台坏掉的摄像头。",
    "Event-level2-4857-Array-1": "* 哦我的天哪！",
    "Event-level2-4857-Array-2": "* 你为什么还没撤离？",
    "Event-level2-4857-Array-3": "* ALPHYS应该通知了所有人才对。",
    "Event-level2-4857-Array-4": "* .#0.25f.#0.25f.",
    "Event-level2-4857-Array-5": "* 等等。",
    "Event-level2-4857-Array-6": "* 你是人类，\n  对吧？",
    "Event-level2-4857-Array-7": "* 你来得可真是时候。",
    "Event-level2-4857-Array-8": "* 我们之中出现了一个\n  滥杀无辜的怪物。",
    "Event-level2-4857-Array-9": "* 所以，#0.25f趁你还能跑，#0.25f \n  快逃吧，人类！",
    "Event-level2-4857-Array-10": "* 我待会儿再跟你算账！",
    "Event-level2-4857-Array-11": "* 哦.#0.25f.#0.25f.",
    "Event-level2-4857-Array-12": "* 我晓得了.#0.25f.#0.25f.",
    "Event-level2-4857-Array-13": "* 好吧，#0.25f\n  这还真有点出乎我的意料。",
    "Event-level2-4857-Array-14": "* 啊.#0.25f.#0.25f.",
    "Event-level2-4857-Array-15": "* 迫不及待想看一场精彩对决了，#0.25f\n  是吧？",
    "Event-level2-4857-Array-16": "* 好吧，#0.25f那么。",
    "Event-level2-4857-Array-17": "* 看来两个怪物之间的\n  战斗必须得推迟了。",
    "Event-level2-4857-Array-18": "* 现在是：一个.#0.25f.#0.25f. \n  呃.#0.25f.#0.25f.\n  战斗.#0.25f.#0.25f.",
    "Event-level2-4857-Array-19": "* 好吧，#0.25f \n  让我们直奔主题吧。",
    "Event-level3-5549-Array-1": "* (今天没有安排任何人。)",
    "Event-level3-5568-Array-1": "* (请勿打扰。)",
    "Event-level3-5569-Array-1": "* 门锁住了。",
    "Event-level3-5586-Array-1": "* 我很抱歉Sans！\n  我从未想过事情会发展到如此地步！",
    "Event-level3-5586-Array-2": "* 但你太过“决心”了！#0.5f\n  必须有人来阻止你！",
    "Event-level3-5586-Array-3": "* 这可能会有点疼。",
    "Event-level3-5586-Array-4": "* 什-#0.25f什么？",
    "Event-level3-5586-Array-5": "* 发生了什么？",
    "Event-level3-5586-Array-6": "* 为什么它不工作？",
    "Event-level3-5586-Array-7": "* 求你了.#0.25f.#0.25f.",
    "Event-level3-5586-Array-8": "* 感谢放我进来。",
    "Event-level3-5598-Array-1": "* (突然间，\n  #0.25f你的目光穿透了另一个维度的屏障。)",
    "Event-level3-5598-Array-2": "",
    "Event-level3-5612-Array-1": "* 终端屏幕上闪烁着绿色的文字信息。",
    "Event-level3-5612-Array-2": "* \"请往这边撤离 -->\"",
    "Event-level3-5613-Array-1": "%redf@0.05f* 不知为何，#0.25f\n  这里从所未有地凌乱。",
    "Event-level3-5614-Array-1": "* 这些书架被暴力地推倒了。",
    "Event-level3-5618-Array-1": "* 这是一张Mettaton的海报。",
    "Event-level3-5628-Array-1": "* (认真的，#0.25f \n  请勿打扰。)",
    "Event-level3-5630-Array-1": "* (没错，#0.25f\n  这些房间全是我租的，\n  告示牌也都是我挂的。)",
    "Event-level3-5630-Array-2": "* (别打扰我。)",
    "Event-level3-5633-Array-1": "* (因这附近发生凶杀事件\n  而暂停营业。)",
    "Event-level3-5655-Array-1": "%redf@0.05f* 真是不可思议，#0.25f\n  这个立方体能有多好看。",
    "Event-level3-5684-Array-1": "%redf@0.05f* 哦，#0.25f\n  快给我们让开！",
    "Event-level3-5684-Array-2": "%redf@0.05f* 我们的武器奈何不了它！",
    "Event-level3-5684-Array-3": "%redf@0.05f* 呵，我们可没时间耗在这上面了。",
    "Event-level3-5684-Array-4": "%redf@0.05f* 我们杀了Alphys然后赶紧\n  离开这儿吧。",
    "Event-level3-5684-Array-5": "%redf@0.05f* 随便吧。",
    "Event-level3-5684-Array-6": "%redf@0.05f* 如果我们过不去，\n  Sans也别想过来。",
    "Event-level3-5684-Array-7": "%redf@0.05f* 继续前进。",
    "Event-level3-5686-Array-1": "@0.0125f* 哎呦，#0.25f\n  这该咋整啊？",
    "Event-level3-5686-Array-2": "* 想想，#0.25fAlphys，#0.25f\n  快想想！",
    "Event-level3-5686-Array-3": "* 等等.#0.25f.#0.25f.",
    "Event-level3-5686-Array-4": "* 决心提取机！",
    "Event-level3-5686-Array-5": "* 我把备用钥匙落在楼上了！",
    "Event-level3-5686-Array-6": "* 他肯定很快就要追下来了！",
    "Event-level3-5687-Array-1": "* 电梯门无法打开。",
    "Event-level3-5689-Array-1": "* 你从地上捡起了一把烧焦的平底锅。",
    "Event-level3-5689-Array-2": "* 物品栏已满。",
    "Event-level3-5689-Array-3": "* 带走吗?",
    "Event-level3-5689-Array-4": "* 你得到了烧焦的平底锅。",
    "Event-level3-5693-Array-1": "* 抽屉是空的。",
    "Event-level3-5755-Array-1": "* 钥匙扣是空的。",
    "Event-level3-5759-Array-1": "%redf@0.05f* 总该有比这更好看的节目在播吧。",
    "Event-level3-5802-Array-1": "%redf@0.05f* 多么美丽的世界啊 =)",
    "Event-level3-5803-Array-1": "* 看起来被关掉了。",
    "Event-level3-5804-Array-1": "* 你在地上找到了传说英雄。",
    "Event-level3-5804-Array-2": "* 你得到了传说英雄。",
    "Event-level3-5812-Array-1": "SANS!",
    "Event-level3-5812-Array-2": "SANS？",
    "Event-level3-5812-Array-3": "噢，#0.25f\n那死骨头又跑哪去了",
    "Event-level3-5812-Array-4": "他为什么又翘班逃跑了？",
    "Event-level3-5812-Array-5": ".#0.25f.#0.25f.",
    "Event-level3-5812-Array-6": "噢!#0.5f\n你好呀!#0.5f",
    "Event-level3-5812-Array-7": "你一定是新来的家伙!",
    "Event-level3-5812-Array-8": "还是.#0.25f.#0.25f.#0.25f？",
    "Event-level3-5812-Array-9": "原谅我的好奇，#0.25f\n但是.#0.25f.#0.25f.",
    "Event-level3-5812-Array-10": "你到底是什么种类\n的怪物呢？",
    "Event-level3-5812-Array-11": "一个内向的怪物，#0.25f \n是么?",
    "Event-level3-5812-Array-12": "哇噢！#0.5f \n多么高尚的一个怪物品种啊！",
    "Event-level3-5812-Array-13": "但失陪了。#0.25f \n现在我还有点事.#0.25f.#0.25f.",
    "Event-level3-5812-Array-14": "我得去找找我的兄弟。",
    "Event-level3-5812-Array-15": "见到你真的非常高兴！",
    "Event-level3-5812-Array-16": "%redf@0.05f* 有点情商吧你。",
    "Event-level3-5812-Array-17": "%redf@0.05f* 我们只需要把这堆废话\n  应付过去就行了。",
    "Event-level3-5824-Array-1": "* (选择一盘录像带观看。)",
    "Event-level3-5824-Array-2": "* (嗵嗵，嗵嗵...)",
    "Event-level3-5824-Array-3": "* 嘿，#0.25f\n  我回来了。",
    "Event-level3-5824-Array-4": "* 真好啊，又能和你聊天啦。#0.5f\n  今天我们来聊聊什么呢？",
    "Event-level3-5824-Array-5": "* 这种生活也确实挺好的。",
    "Event-level3-5824-Array-6": "* (咳咳)。",
    "Event-level3-5824-Array-7": "* 为什么骷髅不去参加舞会？",
    "Event-level3-5824-Array-8": "* 我不知道。#0.5f \n  为什么骷髅不能去跳舞呢？",
    "Event-level3-5824-Array-9": "* 嗐，他找不到舞伴呗，是个光骨司令！",
    "Event-level3-5824-Array-10": "* 噢！#0.5f\n  原来是这样！#0.5f\n  哈哈！",
    "Event-level3-5824-Array-11": "* 好吧，#0.25f\n  看来我要在这儿待一整晚了。",
    "Event-level3-5824-Array-12": "如果我想加入皇家卫队，#0.25f\n首先我就不能让你偷懒！",
    "Event-level3-5824-Array-13": "* 为嘛呢？",
    "Event-level3-5824-Array-14": "因为这会让我显得很丢脸！",
    "Event-level3-5824-Array-15": "* 你用不着我帮忙就已经够难堪了。",
    "Event-level3-5824-Array-16": "* 开玩笑的，#0.25f\n  老兄。",
    "Event-level3-5824-Array-17": "* 嘿，#0.25f等我下班后，#0.25f\n  要不去grillby's吃点？",
    "Event-level3-5824-Array-18": "* 你还从来没去过这里呢。",
    "Event-level3-5824-Array-19": "我还很忙！",
    "Event-level3-5824-Array-20": "好吧！#0.5f \n我跟你去GRILLBY'S吃就是了。",
    "Event-level3-5824-Array-21": "但前提是你得对你的岗位\n上心一点！",
    "Event-level3-5824-Array-22": "* 干啥都行，#0.25f\n  老兄。",
    "Event-level3-5824-Array-23": "* 来嘛，#0.25f\n  就来吃一小口。",
    "Event-level3-5824-Array-24": "* 呃-#0.25f...嗨。",
    "Event-level3-5824-Array-25": "* 嘿你好。",
    "Event-level3-5824-Array-26": "* 你叫什么名字呢？",
    "Event-level3-5824-Array-27": "* 我叫sans.#0.5f\n  那你呢？",
    "Event-level3-5824-Array-28": "* Alphys。",
    "Event-level3-5824-Array-29": "* 酷。#0.5f \n  你手里拿的是啥稀罕玩意？",
    "Event-level3-5824-Array-30": "* 这是我的电视。#0.5f \n  我正在尝试修好它。",
    "Event-level3-5824-Array-31": "* 嗯...#0.5f \n  你看起来挺擅长这个的。",
    "Event-level3-5824-Array-32": "* 谢-#0.25f谢谢你这么说！",
    "Event-level3-5824-Array-33": "* 不用谢。",
    "Event-level3-5824-Array-34": "* 那么，#0.25f \n  你的故事是什么，#0.25f \n  小骷髅？",
    "Event-level3-5824-Array-35": "* 哦，#0.25f你知道的。#0.5f\n  没什么特别的。",
    "Event-level3-5824-Array-36": "* 真的吗？#0.5f\n  每个人都有自己独特的地方。",
    "Event-level3-5824-Array-37": "* 我不造。",
    "Event-level3-5824-Array-38": "* 嗯，#0.25f\n  那你喜欢做什么呢？",
    "Event-level3-5824-Array-39": "* 躺着发呆。",
    "Event-level3-5824-Array-40": "* 你什么都不喜欢做吗？",
    "Event-level3-5824-Array-41": "* 不是。#0.5f\n  我只是懒到骨子里了。",
    "Event-level3-5824-Array-42": "* 嗯，#0.25f\n  看来我们终于发现你的特别之处了。\n  #0.5f嘻嘻，#0.25f嘻嘻。",
    "Event-level3-5824-Array-43": "* 现在，#0.25f\n  你要不要来杯茶呢？",
    "Event-level3-5824-Array-44": "* 好。",
    "Event-level3-5824-Array-45": "-",
    "Event-level3-5852-Array-1": "%redf@0.05f* 别再浪费时间了。",
    "Event-level3-5852-Array-2": "%redf@0.05f* 我们必须集中精力拿下\n  下一次大屠戮。",
    "Event-level3-5854-Array-1": "* 它被一把钥匙锁住了。",
    "Event-level3-5854-Array-2": "* 用钥匙打开了门。",
    "Event-level3-5855-Array-1": "* 柜门敞开着。",
    "Event-level3-5862-Array-1": "* 你偷走了一份垃圾食品。",
    "Event-level3-5862-Array-2": "* (别碰我们的东西。)",
    "Event-level3-5862-Array-3": "* 再偷一份垃圾食品？",
    "Event-level3-5862-Array-4": "* 不过，#0.25f \n  你确实注意到里面有一些垃圾食品。",
    "Event-level3-5862-Array-5": "* 偷点垃圾食品？",
    "Event-level3-5862-Array-6": "* 你在巷子里找到一张纸条。",
    "Event-level3-5862-Array-7": "* (我们，#0.25f那个，#0.25f \n   疏散的时候根本没法卖东西啊。)",
    "Event-level3-5862-Array-8": "* (所以，#0.25f我们算是，\n  #0.25f打烊了。)",
    "Event-level3-5862-Array-9": "* (谨上，#0.25f \n  Bratty和Catty。)",
    "Event-level3-5869-Array-1": "%redf@0.05f* 有人知道这有什么用处吗？",
    "Event-level3-5881-Array-1": "%redf@0.05f* 你是无法杀死一个融合怪的.#0.25f.#0.25f.",
    "Event-level3-5883-Array-1": "* 这是决心提取器的控制面板。",
    "Event-level3-5883-Array-2": "* 看来它没有尽它的责任。",
    "Event-level3-5893-Array-1": "%redf@0.05f* 它到底在保护什么？",
    "Event-level3-5893-Array-2": "%redf@0.05f* 真可爱。",
    "Event-level3-5893-Array-3": "%redf@0.05f* 一定是在保护地底的其他怪物。",
    "Event-level3-5893-Array-4": "%redf@0.05f* 我们继续前进吧。",
    "Event-level3-5909-Array-1": "* 哇偶！",
    "Event-level3-5909-Array-2": "* 看来你发现了一个秘密！",
    "Event-level3-5909-Array-3": "* 没想到还真有人能找到这儿。",
    "Event-level3-5909-Array-4": "* 如果你看到了这条消息，#0.25f \n  记得去我的Gamejolt页面留言\"Toastywaffles\"哦！",
    "Event-level3-5909-Array-5": "* (谨上，#0.25f Evan Streblow)",
    "Event-level3-5977-Array-1": "* (这是一个空的狗粮盆。)",
    "Event-level3-5990-Array-1": "* 工作台看上去无人动过。",
    "Event-level3-5998-Array-1": "* 机器底部有一包薯片。",
    "Event-level3-5998-Array-2": "* 你拿走了炒鸡暑片。",
    "Event-level3-5998-Array-3": "* 自动售货机里已经空空如也。",
    "Event-level3-6021-Array-1": "* 还记得这里吗？",
    "Event-level3-6021-Array-2": "* 我们曾在此处交谈过，#0.25f一次，#0.25f \n  在另一个时间线。",
    "Event-level3-6021-Array-3": "* 我支持过你。",
    "Event-level3-6021-Array-4": "* 我告诉过你，\n  真的有人很在乎你。",
    "Event-level3-6021-Array-5": "* 你一定很怀念那段时光吧，#0.25f\n  不是吗？",
    "Event-level3-6021-Array-6": "* 呵。",
    "Event-level3-6021-Array-7": "* 我也不知道。",
    "Event-level3-6021-Array-8": "@0.1f* 你一定会为你的所作所为后悔的。",
    "Event-level3-6030-Array-1": "%redf@0.05f* 也许她暂时不会再用那个跟踪我们了。",
    "Event-level3-6032-Array-1": "* (长眠于此的是Muffet。)",
    "Event-level3-6032-Array-2": "* 但是，#0.25f \n  感觉还少了点什么。",
    "Event-level3-6032-Array-3": "* 要把金色花放上面吗？",
    "Event-level3-6032-Array-4": "* 你放置了金色花。",
    "Event-level3-6032-Array-5": "* 安息吧。",
    "Event-level3-6032-Array-6": "%redf@0.05f* 我们错过了机会。",
    "Event-level3-6109-Array-1": "* (同样因屠戮事件而关闭。)",
    "Event-level3-6109-Array-2": "* (再说了，#0.25f \n  反正这部电梯也用不了。)",
    "Event-level3-6109-Array-3": "* (所以是双重关闭了，#0.25f\n  我猜？)",
    "Event-level3-6109-Array-4": "* (他们给的工资还不够\n  我贴这些告示的。)",
    "Event-level3-6110-Array-1": "* 海报后面，#0.25f \n  你发现了一把钥匙。",
    "Event-level3-6110-Array-2": "* 你拿走了钥匙。",
    "Event-level3-6124-Array-1": "* (你会后悔你在打扰他们的。)",
    "Event-level3-6141-Array-1": "* 冰箱里有两包方便面。",
    "Event-level3-6141-Array-2": "* (拿一份吗？)",
    "Event-level3-6141-Array-3": "* 你得到了方便面。",
    "Event-level3-6141-Array-4": "* 冰箱里还有一包方便面。",
    "Event-level3-6141-Array-5": "* 冰箱里空空如也。",
    "Event-level4-3147-Array-1": "* 想都别想，#0.25f \n  孩子。",
    "Event-level4-3147-Array-2": "* 你隔着那道屏障可伤不了我。",
    "Event-level4-3164-Array-1": "* 一双忧伤的眼睛凝视着你。",
    "Event-level4-3170-Array-1": "%redf@0.05f* 不，不，不。",
    "Event-level4-3170-Array-2": "%redf@0.05f* 我们还要找到那个骷髅。",
    "Event-level4-3182-Array-1": "* 锁住了...",
    "Event-level4-3202-Array-1": "* (汪汪。)",
    "Event-level4-3225-Array-1": "* 入口处积雪成堆。",
    "Event-level4-3226-Array-1": "%redf@0.05f* 你当然知道这盒子是干嘛的，#0.25f\n  傻瓜。",
    "Event-level4-3248-Array-1": "* 亲爱的Sans，#0.25f\n  我好像到处都找不到你。",
    "Event-level4-3248-Array-2": "* 如果你在读这个，#0.25f\n  请尽快回来找我！",
    "Event-level4-3248-Array-3": "* 你的兄弟，#0.25f \n  Papyrus。",
    "Event-level4-3255-Array-1": "%redf@0.05f* 别让他跑了！",
    "Event-level4-3257-Array-1": "* 拿一块糖果？",
    "Event-level4-3257-Array-2": "* 奇怪的是，那是唯一剩下的糖了。",
    "Event-level4-3357-Array-1": "%redf@0.05f* 没时间收礼物了。",
    "Event-level4-3373-Array-1": "* 桥下藏着一台损坏的摄像头。",
    "Event-level4-3381-Array-1": "* 没有人料到\n  Sans会这么做.#0.25f.#0.25f.",
    "Event-level4-3381-Array-2": "* 起初，#0.25f \n  我们都以为他又像\n  往常一样在开玩笑。",
    "Event-level4-3381-Array-3": "* 但是那双眼睛.#0.25f.#0.25f.#0.5f \n  令所有人都汗毛直竖。",
    "Event-level4-3381-Array-4": "* 我完全没想到事态会变成这样。",
    "Event-level4-3381-Array-5": "* .#0.25f#0.25f..",
    "Event-level4-3381-Array-6": "* 不过，我想你和他也没什么两样。#0.25f",
    "Event-level4-3381-Array-7": "* 我在你身上也看到了同样的眼神。",
    "Event-level4-3381-Array-8": "* 你的存在就是个错误,#0.25f\n  不是吗？",
    "Event-level4-3381-Array-9": "* 一边在屠戮，#0.25f\n  另一边在争夺。",
    "Event-level4-3381-Array-10": "* 到了最后，#0.25f\n  谁会成为赢家？",
    "Event-level4-3381-Array-11": "* Papyrus也是，#0.25f\n  嗯？",
    "Event-level4-3381-Array-12": "%redf@0.05f* 他到底在说啥？",
    "Event-level4-3383-Array-1": "SANS？#0.5f\n你怎么能这样？！",
    "Event-level4-3383-Array-2": "* 不.#0.25f.#0.25f. 不是.#0.25f.#0.25f. 因为那个人类.#0.25f.#0.25f.",
    "Event-level4-3383-Array-3": "* 人类曾经对你下此毒手.#0.25f.#0.25f. \n  而且.#0.25f.#0.25f.",
    "Event-level4-3383-Array-4": "* 他们不会善罢甘休的.#0.25f.#0.25f. \n  他们会一次又一次地将你置于死地.#0.25f.#0.25f.",
    "Event-level4-3383-Array-5": "* 所以.#0.25f.#0.25f.\n  呃.#0.25f.#0.25f.",
    "Event-level4-3383-Array-6": "* 我将会终-#0.25f终止这一切。",
    "Event-level4-3383-Array-7": "SANS！#0.5f \n你不可以.#0.25f.#0.25f.",
    "Event-level4-3383-Array-8": "SANS！#0.5f 住手！#0.5f\n一定还有别的办法的！",
    "Event-level4-3383-Array-9": "我们可以和这个人类谈谈！",
    "Event-level4-3383-Array-10": "我们可以试着和他们讲和！",
    "Event-level4-3383-Array-11": "只要我们足够信任他们，#0.25f\n我相信他们一定能改过自新的！",
    "Event-level4-3383-Array-12": "* 这.#0.25f.#0.25f.",
    "Event-level4-3383-Array-13": "* 这样更好，#0.25f 兄弟。#0.5f \n  但如果我饶你一命的话.#0.25f.#0.25f.",
    "Event-level4-3383-Array-14": "求你了！",
    "Event-level4-3383-Array-15": "SANS.#0.25f.#0.25f. \n我.#0.25f.#0.25f.",
    "Event-level4-3383-Array-16": "我明白了。",
    "Event-level4-3383-Array-17": "如果这能让你感到开心的话.#0.25f.#0.25f.",
    "Event-level4-3383-Array-18": "那我也能坦然面对死亡了！",
    "Event-level4-3383-Array-19": "* 不#0.25f要#0.25f.#0.25f.#0.25f.#0.25f #0.25f兄#0.25f-#0.25f弟#0.25f.#0.25f.#0.25f.#0.25f",
    "Event-level4-3383-Array-20": "* 为什么.#0.25f.#0.25f.#0.25f？",
    "Event-level4-3383-Array-21": "@0.0125f* 这全都是人类的错！",
    "Event-level4-3383-Array-22": "@0.0125f* 是他们逼我这么做的！",
    "Event-level4-3383-Array-23": "@0.0125f* 这都是他们的错！",
    "Event-level4-3383-Array-24": "* 都是他们的错……",
    "Event-level4-3383-Array-25": "* 呵.#0.25f.#0.25f. 呵.#0.25f.#0.25f.",
    "Event-level4-3383-Array-26": "@0.00625f哈哈哈哈哈哈哈哈哈哈哈哈哈哈哈哈哈哈哈哈哈哈哈哈哈哈哈哈哈哈哈哈哈哈哈哈哈哈哈哈哈哈哈哈哈哈哈哈哈哈哈！",
    "Event-level4-3383-Array-27": "* 噢.#0.25f.#0.25f.",
    "Event-level4-3383-Array-28": "%redf@0.05f* 他又要来抢我们的EXP了！",
    "Event-level4-3383-Array-29": "%redf@0.05f* 冲上前去干掉他！#0.5f\n  快！！！",
    "Event-level4-3383-Array-30": "%redf@0.05f* 我们被困住了！",
    "Event-level4-3383-Array-31": "%redf@0.05f* 你竟敢违抗我？！",
    "Event-level4-3383-Array-32": "* 真的是太好笑了。",
    "Event-level4-3390-Array-1": "* (铃，铃...)",
    "Event-level4-3390-Array-2": "",
    "Event-level4-3390-Array-3": "你真以为我无法掌控这个世界吗？",
    "Event-level4-3390-Array-4": "",
    "Event-level4-3390-Array-5": "",
    "Event-level4-3390-Array-6": "",
    "Event-level4-3390-Array-7": "",
    "Event-level4-3390-Array-8": "* (滴...)",
    "Event-level4-3390-Array-9": "",
    "Event-level4-3390-Array-10": "",
    "Event-level4-3390-Array-11": "",
    "Event-level4-3390-Array-12": "",
    "Event-level4-3390-Array-13": "",
    "Event-level4-3395-Array-1": "%redf@0.05f* 又放他一马.#0.25f.#0.25f.",
    "Event-level4-3519-Array-1": "* (懒得再步行穿过雪镇？)",
    "Event-level4-3519-Array-2": "* (试试这个雪下隧道！)",
    "Event-level4-3519-Array-3": "* (它设计地十分快捷便利。)",
    "Event-level4-3593-Array-1": "* 树林间藏着一台坏掉的摄像头。",
    "Event-level5-7323-Array-1": "@0.05f%redf * 这条路已经没有EXP可获取了。",
    "Event-level5-7323-Array-2": "@0.05f%redf * 最终对决的时刻到了。",
    "Event-level5-7347-Array-1": "@0.05f%redf * 这条路仍然没有EXP。",
    "Event-level5-7493-Array-1": "* 下次重置见，#0.25f\n  孩子。",
    "Event-level5-7619-Array-1": "* 王座。",
    "Event-level5-7846-Array-1": "@0.05f%redf * 您好。",
    "Event-level5-7846-Array-2": "@0.05f%redf * 很惊讶会见到我吗？",
    "Event-level5-7846-Array-3": "@0.05f%redf * 你真的不该这样。",
    "Event-level5-7846-Array-4": "@0.05f%redf * 我们是一个团队，#0.25f\n  记得吗？",
    "Event-level5-7846-Array-5": "@0.05f%redf * 作为你的队友，#0.25f\n  我想为你祝贺。",
    "Event-level5-7846-Array-6": "@0.05f%redf * 在一起，#0.25f\n  我们做到了。",
    "Event-level5-7846-Array-7": "@0.05f%redf * 我们又一次征服了这个世界。",
    "Event-level5-7846-Array-8": "@0.05f%redf * 我们抵达了绝对的终点。",
    "Event-level5-7846-Array-9": "@0.05f%redf * 327。",
    "Event-level5-7846-Array-10": "@0.05f%redf * 这需要多少次路线\n  才能带来的改变。",
    "Event-level5-7846-Array-11": "@0.05f%redf * 为了这个世界的蜕变。",
    "Event-level5-7846-Array-12": "@0.05f%redf * 起初我并不知道你在做什么。",
    "Event-level5-7846-Array-13": "@0.05f%redf * 当我们刚刚完成了第一条路线的时候。",
    "Event-level5-7846-Array-14": "@0.05f%redf * Sans确实是个难缠的对手，#0.25f\n  不过我们终究还是成功了。",
    "Event-level5-7846-Array-15": "@0.05f%redf * 之后，#0.25f\n  你把灵魂给我来重置你的世界。",
    "Event-level5-7846-Array-16": "@0.05f%redf * 我以为那就是你杀戮的终点了。",
    "Event-level5-7846-Array-17": "@0.05f%redf * 但我错了。",
    "Event-level5-7846-Array-18": "@0.05f%redf * 你重置了，#0.25f\n  然后又重蹈覆辙。",
    "Event-level5-7846-Array-19": "@0.05f%redf * 你亲手摧毁了那个用灵魂换来的世界。",
    "Event-level5-7846-Array-20": "@0.05f%redf * 我不明白。",
    "Event-level5-7846-Array-21": "@0.05f%redf * 在第二条路线结束时，#0.25f\n  我想或许另一条路线更适合你。",
    "Event-level5-7846-Array-22": "@0.05f%redf * 但你仍继续前行。#0.5f\n  你又一次出卖了你的灵魂。",
    "Event-level5-7846-Array-23": "@0.05f%redf * 在你第九次轮回即将结束时，#0.25f\n  我终于明白了你的所作所为。",
    "Event-level5-7846-Array-24": "@0.05f%redf * 你曾试图确认是否有什么，#0.5f\n  哪怕一丝一毫的变化。",
    "Event-level5-7846-Array-25": "@0.05f%redf * 但什么也没有发生。",
    "Event-level5-7846-Array-26": "@0.05f%redf * 然后你放弃了。",
    "Event-level5-7846-Array-27": "@0.05f%redf * 在你停手之前，\n  为了你那小小的“实验”，\n  你已经卖给了我9个灵魂。",
    "Event-level5-7846-Array-28": "@0.05f%redf * 在你感到厌倦之前。",
    "Event-level5-7846-Array-29": "* 我很快就明白了，\n  那些灵魂为我所做的一切。",
    "Event-level5-7846-Array-30": "@0.05f%redf * 9个灵魂的力量正\n  将我变为一个神明。",
    "Event-level5-7846-Array-31": "@0.05f%redf * 我感受到了你的灵魂的力量。",
    "Event-level5-7846-Array-32": "@0.05f%redf * 我不再渴望前往下一个世界了。",
    "Event-level5-7846-Array-33": "@0.05f%redf * 我只想留在此地，#0.25f\n  不停地收集灵魂。",
    "Event-level5-7846-Array-34": "@0.05f%redf * 我渐渐爱上了这个世界。",
    "Event-level5-7846-Array-35": "@0.05f%redf * 当你退出时，#0.25f\n  我开始了。",
    "Event-level5-7846-Array-36": "@0.05f%redf * 我掌控了你的身体。",
    "Event-level5-7846-Array-37": "@0.05f%redf * 并且不断完成各种路线。",
    "Event-level5-7846-Array-38": "@0.05f%redf * 我获得了远超任何人想象的力量。",
    "Event-level5-7846-Array-39": "",
    "Event-level5-7846-Array-40": "",
    "Event-level5-7846-Array-41": "",
    "Event-level5-7846-Array-42": "",
    "Event-level5-7846-Array-43": "",
    "Event-level5-7846-Array-44": "",
    "Event-level5-7846-Array-45": "",
    "Event-level5-7846-Array-46": "",
    "Event-level5-7846-Array-47": "",
    "Event-level5-7846-Array-48": "",
    "Event-level5-7846-Array-49": "",
    "Event-level5-7846-Array-50": "",
    "Event-level5-7846-Array-51": "",
    "Event-level5-7846-Array-52": "",
    "Event-level5-7846-Array-53": "",
    "Event-level5-7846-Array-54": "",
    "Event-level5-7846-Array-55": "",
    "Event-level5-7846-Array-56": "",
    "Event-level5-7846-Array-57": "",
    "Event-level5-7846-Array-58": "",
    "Event-level5-7846-Array-59": "",
    "Event-level5-7846-Array-60": "@0.05f%redf * 下次重置之后见，#0.25fFrisk。",
    "Event-level5-7846-Array-61": "@0.05f%redf * 等等，\n  #0.25f我们之前经历过这个，\n  #0.25f不是吗？",
    "Event-level5-7846-Array-62": "",
    "Event-level5-7846-Array-63": "",
    "Event-level5-7846-Array-64": "@0.05f%redf * 你又为我带来了一个灵魂。",
    "Event-level5-7846-Array-65": "",
    "Event-level5-7846-Array-66": "",
    "Event-level5-7846-Array-67": "",
    "Event-level5-7846-Array-68": "",
    "Event-level5-7846-Array-69": "",
    "Event-level5-7846-Array-70": "",
    "Event-level5-7846-Array-71": "",
    "Event-level5-7846-Array-72": "",
    "Event-level5-7846-Array-73": "",
    "Event-level5-7846-Array-74": "",
    "Event-level5-7846-Array-75": "",
    "Event-level5-7846-Array-76": "",
    "Event-level5-7846-Array-77": "",
    "Event-level5-7846-Array-78": "",
    "Event-level5-7846-Array-79": "",
    "Event-level5-7846-Array-80": "",
    "Event-level5-7846-Array-81": "",
    "Event-level5-7846-Array-82": "",
    "Event-level5-7846-Array-83": "",
    "Event-level5-7846-Array-84": "",
    "Event-level5-7846-Array-85": "",
    "Event-level5-7846-Array-86": "",
    "Event-level5-7846-Array-87": "",
    "Event-level5-7846-Array-88": "",
    "Event-level5-7846-Array-89": "@0.05f%redf * 而就在我意识到的那一刻，#0.25f \n  我又会再次忘记。",
    "Event-level5-7846-Array-90": "",
    "Event-level5-7846-Array-91": "",
    "Event-level5-7846-Array-92": "",
    "Event-level5-7846-Array-93": "",
    "Event-level5-7846-Array-94": "",
    "Event-level5-8006-Array-1": "* (安息。)",
    "Event-level7-6877-Array-1": "--",
    "Event-level7-6877-Array-2": "* 上面写着 \n  \"蜘蛛果汁 - 18G\"。",
    "Event-level7-6877-Array-3": "* 偷一个？",
    "Event-level7-6877-Array-4": "* 你偷了一瓶蜘蛛果汁。",
    "Event-level7-6877-Array-5": "* 售罄。",
    "Event-level7-6880-Array-1": "%redf@0.05f* 永远在装修中的房间。",
    "Event-level7-6887-Array-1": "* 新鲜出炉的。",
    "Event-level7-6887-Array-2": "* 你得到了派。",
    "Event-level7-6988-Array-1": "* 这只是一朵金色花。",
    "Event-level7-6988-Array-2": "* 你拾起了金色花。",
    "Event-level7-7145-Array-1": "* 蜘蛛烘焙义卖会。",
    "Event-level7-7145-Array-2": "* 所有收益都将捐赠给真正的蜘蛛。",
    "Event-level7-7160-Array-1": "%redf@0.05f* 你没见过尘埃吗？",
    "Event-level7-7222-Array-1": "* 已经难以辨识上面的文字了。#0.5f \n  就连标记几乎也已经褪尽。",
    "Event-level7-7222-Array-2": "%redf@0.05f* 看来有人在我们来之前\n  忘记重新粉刷了。",
    "Event-level7-7236-Array-1": "%redf@0.05f* 这只是一个摆满书的架子。",
    "Event-level7-7236-Array-2": "%redf@0.05f* 这到底有什么好玩的？",
    "Event-level7-7251-Array-1": "* 顺着路走。",
    "Event-level7-7286-Array-1": "%redf@0.05f* 你指望能找到谁呢？",
    "Event-level7-7305-Array-1": "* \"按 [Z] 阅读标牌！\"",
    "Event-level7-7317-Array-1": "%redf@0.05f* ?",
    "Event-level7-7317-Array-2": "%redf@0.05f* 所以，妈妈去哪了？",
    "Event-level7-7317-Array-3": "*%whitef 你好，#0.25f我的孩子。#0.5f \n  我希望你没有等候太久。",
    "Event-level7-7317-Array-4": "* 我刚刚，#0.25f放了一个人进来。#0.5f \n  他需要一点东西。",
    "Event-level7-7317-Array-5": "* 我希望他能很快找到\n  自己想要的东西。",
    "Event-level7-7317-Array-6": "* 真奇怪啊，#0.25f 不过...#0.5f \n  他看起来真的好眼熟啊...",
    "Event-level7-7317-Array-7": "* 哦对了！#0.5f \n  我还没自我介绍呢！",
    "Event-level7-7317-Array-8": "* 我为什么要拿一堆\n  鸡毛蒜皮的小事\n  来骚扰一个孩子呢？",
    "Event-level7-7317-Array-9": "* 我叫Toriel,#0.25f\n  Ruins的管理者。",
    "Event-level7-7317-Array-10": "* 我每天都会经过这里，\n  来看看有没有人掉下来。",
    "Event-level7-7317-Array-11": "* 在此之前已经好久\n  都没有人类到来了。",
    "Event-level7-7317-Array-12": "* 来吧。#0.5f \n  让我带你离开这个地下坟墓吧。",
    "Event-level7-7317-Array-13": "* 这边走。",
    "Event-level7-7317-Array-14": "* 哦！#0.5f 我的电话响了！",
    "Event-level7-7317-Array-15": "* 请稍等一下，#0.25f 我的孩子。",
    "Event-level7-7317-Array-16": "* 喂？",
    "Event-level7-7317-Array-17": "* ...",
    "Event-level7-7317-Array-18": "* 你怎么会知道我的...？",
    "Event-level7-7317-Array-19": "* 但是，#0.25f \n  我还要陪着...",
    "Event-level7-7317-Array-20": "* 什么？#0.5f \n  哎呀，没必要生气嘛。",
    "Event-level7-7317-Array-21": "* 不不,#0.25f你说得对。#0.5f \n  那件事确实挺重要。",
    "Event-level7-7317-Array-22": "* 对不起，我的孩子。",
    "Event-level7-7317-Array-23": "* 我得要离开一会。",
    "Event-level7-7317-Array-24": "* 但请你相信我,#0.25f \n  我不会因为一件鸡毛蒜皮的小事\n  就丢下你不管的。",
    "Event-level7-7317-Array-25": "* 在我回来之前，\n  请你在此处耐心等候。",
    "Event-level7-7317-Array-26": "%redf@0.05f* 这里到底发生了什么？",
    "Event-level7-7317-Array-27": "%redf@0.05f* 我有种预感她不会回来了。#0.5f \n  我们走吧！",
    "Event-level7-7317-Array-28": "* 我们必须确保每个人\n  的安全。",
    "Event-level7-7317-Array-29": "* 我会尽快赶到的。",
    "Event-level7-7347-Array-1": "%redf@0.05f* 我们的刀去哪了？",
    "Event-level7-7448-Array-1": "%redf@0.05f* 哎呦，得了吧。",
    "Event-level7-7448-Array-2": "%redf@0.05f* 你我都清楚，那才是\n  我们的真面目。",
    "Event-level7-7463-Array-1": "%redf@0.05f* 只是一朵花。",
    "Event-level7-7541-Array-1": "@0.03f* 他走了吗？",
    "Event-level7-7541-Array-2": "@0.03f* 哦#0.5f.#0.5f.#0.5f.",
    "Event-level7-7541-Array-3": "@0.03f* 我真没想到你竟然\n  也在这儿#0.5f.#0.5f.#0.5f.",
    "Event-level7-7541-Array-4": "@0.03f* 不过没有关系#0.5f.#0.5f.#0.5f.",
    "Event-level7-7541-Array-5": "@0.03f* 我会换个地方躲起来。",
    "Event-level7-7587-Array-1": "* 唯有勇者方可前行。",
    "Event-level7-7587-Array-2": "* 勇敢的人，愚蠢的人。\n  都不走中间的路。",
    "Event-level7-7621-Array-1": "* 久等了，我回来了。#0.5f \n  感谢你的耐心。",
    "Event-level7-7621-Array-2": "* 我得要快点把这事搞定。",
    "Event-level7-7621-Array-3": "* 那么，#0.25f关于这个\"杀手\"。#0.5f\n  既然Ruins已经安全了，#0.25f\n  下一步该怎么做呢？",
    "Event-level7-7621-Array-4": "* 唔.#0.25f.#0.25f.#0.25f?",
    "Event-level7-7621-Array-5": "* 怎么了吗？",
    "Event-level7-7621-Array-6": "* 杀手已经伤害不了我们了。",
    "Event-level7-7621-Array-7": "* 这里已经不需要再担惊受怕了。",
    "Event-level7-7621-Array-8": "* 唔.#0.25f.#0.25f.#0.25f好吧.#0.25f.#0.25f.",
    "Event-level7-7621-Array-9": "* 我.#0.25f.#0.25f.",
    "Event-level7-7621-Array-10": "* 你就是他，#0.25f对吧？",
    "Event-level7-7621-Array-11": "* 你跟我讲的那些笑话。",
    "Event-level7-7621-Array-12": "* 那些坐在门前的时光.#0.25f.#0.25f.",
    "Event-level7-7621-Array-13": "* 我信任过你。",
    "Event-level7-7621-Array-14": "* 你告-#0.25f告诉我这事多么重要。",
    "Event-level7-7621-Array-15": "* 所以，#0.25f \n  我唯一该提防的杀手.#0.25f.#0.25f.",
    "Event-level7-7621-Array-16": "* 就是你。",
    "Event-level7-7621-Array-17": "%redf@0.05f* 他刚刚偷了我们的EXP！",
    "Event-level7-7621-Array-18": "* 为何不吃一块刚出炉\n  的派定定神呢？",
    "Event-level7-7656-Array-1": "%redf@0.05f* 不必客气。",
    "Event-level7-7672-Array-1": "%redf@0.05f* 这是她最钟爱的。",
    "Event-level7-7703-Array-1": "%redf@0.05f* 哎哟喂，您瞧瞧！",
    "Event-level7-7703-Array-2": "%redf@0.05f* 这朵是红花诶。",
    "Event-level7-7724-Array-1": "%redf@0.05f* 你给我打住。\n  我们的任务还没完成呢。",
    "Event-level7-7724-Array-2": "%redf@0.05f* 你真以为有人会请你进去吗？",
    "Event-level7-7724-Array-3": "%redf@0.05f* 你在浪费你宝贵的时间。",
    "Event-level7-7724-Array-4": "%redf@0.05f* 再在这儿待下去纯属浪费时间。",
    "Event-level7-7773-Array-1": "*上面写着\n  \"蜘蛛甜甜圈 - 7G\"。",
    "Event-level7-7773-Array-2": "* 你偷了一个蜘蛛甜甜圈。",
    "Event-level7-7802-Array-1": "%redf@0.05f* 忘掉它吧。",
    "Event-level7-7802-Array-2": "%redf@0.05f* 它们都太钝了，\n  根本没法用。",
    "Event-level7-7809-Array-1": "%redf@0.05f* 你要去哪？",
    "Event-level7-7809-Array-2": "%redf@0.05f* 这个房间里还有EXP可以获取。",
    "Event-level7-7810-Array-1": "* 西边的房间是东边房间的蓝图。",
    "Event-level7-7887-Array-1": "%redf@0.05f* 我绝不容忍任何仁慈。",
    "Event-level7-7896-Array-1": "%redf@0.05f* 你为何对这如此着迷？",
    "Event-level7-7921-Array-1": "* 你拿走了玩具刀。",
    "Event-level7-7953-Array-1": "* 看来壁炉已经熄灭了。#0.5f\n  还会有人去重新点燃它吗。",
    "Event-level9-3486-Array-1": "* 铃铛被顶歪了。",
    "Event-level9-3486-Array-2": "* 要把它摆正吗？",
    "Event-level9-3486-Array-3": "* 铃铛被摆正了。",
    "Event-level9-3490-Array-1": "* (这是一个箱子。)",
    "Event-level9-3490-Array-2": "* (你可以放入或取出物品。)",
    "Event-level9-3490-Array-3": "* (不过，为什么要这么做呢？？？)",
    "Event-level9-3490-Array-4": "* (你又不能使用箱子里的物品！)",
    "Event-level9-3490-Array-5": "* (谨上，一个箱子厌恨者。)",
    "Event-level9-3491-Array-1": "@0.075f* 你背叛了所有怪物同胞！",
    "Event-level9-3491-Array-2": "@0.075f* 你这个走狗。",
    "Event-level9-3491-Array-3": "@0.075f* Papyrus一定会以你\n  这个兄弟为耻辱的。",
    "Event-level9-3491-Array-4": "@0.0125f* 闭上你的嘴然后给爷爬！",
    "Event-level9-3491-Array-5": "@0.075f* 你杀不死我的！",
    "Event-level9-3491-Array-6": "@0.075f* 因为我拒绝死亡！",
    "Event-level9-3491-Array-7": "%redf@0.05f* 她分心了！",
    "Event-level9-3491-Array-8": "%redf@0.05f* 赶紧杀掉她吧，#0.25f\n  趁现在还来得及！",
    "Event-level9-3491-Array-9": "%redf@0.05f* 让我来。",
    "Event-level9-3491-Array-10": "%redf@0.05f* 好吧，#0.25f 那么。#0.5f\n  我自己来！",
    "Event-level9-3491-Array-11": "* 你胜利了！\n* 你得到了 250 EXP和 0 金钱。",
    "Event-level9-3491-Array-12": "* 你的LOVE增加到了7。",
    "Event-level9-3491-Array-13": "* 什么#0.25f.#0.25f.#0.25f.",
    "Event-level9-3491-Array-14": "* 好吧！#0.5f好吧！",
    "Event-level9-3491-Array-15": "* 好的，#0.25fPapyrus，#0.25f\n  我明白了！",
    "Event-level9-3491-Array-16": "* 我知道这是\n  人类先抢到的！",
    "Event-level9-3491-Array-17": "* 不，#0.25f \n  我也不知道接下来该做什么。",
    "Event-level9-3491-Array-18": "* 我会想办法的！",
    "Event-level9-3491-Array-19": "* 不！",
    "Event-level9-3525-Array-1": "* 一尊破碎的音乐盒静卧于雕像之中。",
    "Event-level9-3526-Array-1": "* 入口被什么东西堵住了。",
    "Event-level9-3728-Array-1": "",
    "Event-level9-3728-Array-2": "",
    "Event-level9-3741-Array-1": "* 当四朵桥花在水中\n  排成一条线时，#0.25f\n  它们就会绽放。",
    "Event-level9-3768-Array-1": "* 当解谜失误时...",
    "Event-level9-3768-Array-2": "* 铃铛能将桥花唤回到最初位置。",
    "Event-level9-3852-Array-1": "* 噢。",
    "Event-level9-3852-Array-2": "* 你不是他。",
    "Event-level9-3852-Array-3": "* 抱歉。",
    "Event-level9-3856-Array-1": "%redf@0.05f* 老规矩了。",
    "Event-level9-3856-Array-2": "",
    "Event-level9-3857-Array-1": "* 瀑布后面有一台损坏的摄像头。",
    "Event-level9-3909-Array-1": "* Papyrus，#0.25f \n  你在那吗？",
    "Event-level9-3974-Array-1": "* 长椅下什么也不剩了。",
    "Event-level9-3977-Array-1": "* 嗯。#0.5f好吧，#0.25f \n  不必客气我把你放在这里。",
    "InteractNPC-level2-4010-Array-1": "* Whimsun撞到了你！",
    "InteractNPC-level2-4010-Array-2": "* Whimsun - 攻击 1 防御 0 \n* 它不知所措。",
    "InteractNPC-level2-4010-Array-3": "请...",
    "InteractNPC-level2-4010-Array-4": "* 查看",
    "InteractNPC-level2-4010-Array-5": "0",
    "InteractNPC-level2-4360-Array-1": "* 好戏开场了。",
    "InteractNPC-level2-4360-Array-2": "* METTATON NEO - 攻击 5 防御 10 \n* 这将会是一场精彩的表演。",
    "InteractNPC-level2-4360-Array-3": "...",
    "InteractNPC-level2-4360-Array-4": "我们才刚见面，现在却要生死相搏。真是可惜啊。",
    "InteractNPC-level2-4360-Array-5": "我并不憎恨人类本身。恰恰相反。我只是需要你的灵魂。",
    "InteractNPC-level2-4360-Array-6": "地下世界的局势一旦好转，我就会打破结界。",
    "InteractNPC-level2-4360-Array-7": "数百万人类都将知晓\"METTATON\"的大名！",
    "InteractNPC-level2-4826-Array-1": "* Washua跌跌撞撞地走了过来。",
    "InteractNPC-level2-4826-Array-2": "* Washua - 攻击 3 防御 5 \n* 只想待在一个干净的地方。",
    "InteractNPC-level2-4826-Array-3": "太多布满污点的灵魂...",
    "InteractNPC-level2-4826-Array-4": "绿色代表洁净...",
    "InteractNPC-level2-4826-Array-5": "我想念我的朋友们……",
    "InteractNPC-level2-4826-Array-6": "孤身一人……",
    "InteractNPC-level4-3404-Array-1": "* 总算逮着他了。",
    "InteractNPC-level4-3404-Array-2": "* Sans - 攻击 ??? 防御 ??? \n* 尚未准备充足。",
    "InteractNPC-level4-3404-Array-3": "你不能...",
    "InteractNPC-level4-3404-Array-4": "你还不能来这！",
    "InteractNPC-level4-3404-Array-5": "我还没准备好！",
    "InteractNPC-level4-3404-Array-6": "我还没……",
    "InteractNPC-level4-3404-Array-7": "我还没有足够的...",
    "InteractNPC-level4-3404-Array-8": "你...",
    "InteractNPC-level4-3404-Array-9": "打了...",
    "InteractNPC-level4-3404-Array-10": "我...",
    "InteractNPC-level5-7497-Array-1": "* 玉盘素影，漫溢廊间。",
    "InteractNPC-level5-7497-Array-2": "* 他的决心愈发强大。",
    "InteractNPC-level5-7497-Array-3": "* Sans - 攻击 ??? 防御 ??? \n* 现在，他准备好了。",
    "InteractNPC-level5-7497-Array-4": "* 你站着不动。",
    "InteractNPC-level5-8057-Array-1": "",
    "InteractNPC-level5-8057-Array-2": "",
    "InteractNPC-level5-8057-Array-3": "",
    "InteractNPC-level5-8057-Array-4": "",
    "InteractNPC-level5-8057-Array-5": "",
    "InteractNPC-level5-8057-Array-6": "",
    "InteractNPC-level5-8057-Array-7": "",
    "InteractNPC-level7-7033-Array-1": "* 一只Froggit跳到了你的面前。",
    "InteractNPC-level7-7033-Array-2": "* Froggit - 攻击 2 防御 2 \n* 不知所措，但仍感到恐惧。",
    "InteractNPC-level7-7033-Array-3": "呱呱...",
    "InteractNPC-level7-7033-Array-4": "呱...",
    "InteractNPC-level7-7033-Array-5": "喵...",
    "InteractNPC-level7-7124-Array-1": "* Loox坚守阵地。",
    "InteractNPC-level7-7124-Array-2": "* LOOX - 攻击 3 防御 4 \n* 准备好采取行动了。",
    "InteractNPC-level7-7124-Array-3": "我绝不允许你欺负\n我的朋友。",
    "InteractNPC-level7-7124-Array-4": "我看透你了。",
    "InteractNPC-level7-7124-Array-5": "是时候采取行动了。",
    "InteractNPC-level7-7124-Array-6": "先是他的到来，\n现在又是你。\n为什么？",
    "InteractNPC-level7-7559-Array-1": "* 伤害 - 1 防御 - 0 \n* 他在发抖。",
    "InteractNPC-level7-7559-Array-2": "* 你告诉Whimsun你不会伤害他。",
    "InteractNPC-level7-7559-Array-3": "谢谢你！",
    "InteractNPC-level7-7559-Array-4": "* 安慰",
    "InteractNPC-level7-7559-Array-5": "1",
    "InteractSparkle-level2-4904-Array-1": "",
    "InteractSparkle-level2-4904-Array-2": "",
    "InteractSparkle-level2-4904-Array-3": "* 相反，这些闪光点充当了\"存档点\"的功能。",
    "InteractSparkle-level2-4904-Array-4": "",
    "InteractSparkle-level2-4904-Array-5": "",
    "InteractSparkle-level2-4904-Array-6": "",
    "InteractSparkle-level2-4904-Array-7": "* (Ruins的阴影笼罩在上方，这使你充满了决心。)",
    "InteractSparkle-level2-4904-Array-8": "",
    "ManageCutscene-level6-133-Array-1": "所以...",
    "ManageCutscene-level6-133-Array-2": "@0.05f看来结局早已注定，#0.4f\n是吗?",
    "ManageCutscene-level6-133-Array-3": "@0.04f...",
    "ManageCutscene-level6-133-Array-4": "但是...",
    "ManageCutscene-level6-133-Array-5": "不要说我\n没警告过你。",
    "ManageCutscene-level6-133-Array-6": "好吧。",
    "ManageCutscene-level6-133-Array-7": "我要去grillby's了。",
    "ManageCutscene-level6-133-Array-8": "papyrus,#0.5f \n你想要来点什么吗？",
    "ManageCutscene-level6-133-Array-9": "@0.06f327次屠杀线转瞬即逝#0.5f.#0.5f.#0.5f.",
    "ManageCutscene-level6-133-Array-10": "Chara随着每条新路线的推进\n而愈发强大。",
    "ManageCutscene-level6-133-Array-11": "拥有了Chara的强大力量，\n#0.5f人类再也无法掌控自己的身体。",
    "ManageCutscene-level6-133-Array-12": "然后，Chara建立起了\n永无止境的屠杀循环。",
    "ManageCutscene-level6-133-Array-13": "但是突然，#0.5fSans想起了#0.5f.#0.5f.#0.5f.",
    "ManageCutscene-level6-133-Array-14": "他想起了玩家在每条路线的所作所为，\n回忆不断在他的脑海中徘徊#0.5f.#0.5f.#0.5f.",
    "ManageCutscene-level6-133-Array-15": "痛苦#0.5f.#0.5f.#0.5f.#0.5f暴力#0.5f.#0.5f.#0.5f.",
    "ManageCutscene-level6-133-Array-16": "#0.5f.#0.5f.#0.5f.",
    "ManageCutscene-level6-133-Array-17": "现在，#2f他下定决心要扭转这局势。",
    "ManagePlayer-level2-4064-Array-1": "雪块",
    "ManagePlayer-level5-7140-Array-1": "Sans2",
    "ManageText_GameOver-level1-37-Array-1": "哎呀，别这样。",
    "ManageText_GameOver-level1-37-Array-2": "快起来！",
    "ManageText_GameOver-level1-37-Array-3": "你的实力足以碾压他们。",
    "ManageText_GameOver-level1-37-Array-4": "配合一下行不行！",
    "ManageText_GameOver-level1-37-Array-5": "快起来！",
    "ManageText_GameOver-level1-37-Array-6": "我们还有更重要的事情去做。",
    "ManageText_GameOver-level1-37-Array-7": "你就这点本事？",
    "ManageText_GameOver-level1-37-Array-8": "真可悲。",
    "ManageText_GameOver-level1-37-Array-9": "嘿，别睡了！",
    "ManageText_GameOver-level1-37-Array-10": "是时候了！",
    "SaveLoad-level0-174-Array-1": "螃果"
}
