{
    "EXTRA_LINES_TEST-0": "",
    "EXTRA_LINES_TEST-1": "",
    "EXTRA_LINES_TEST-2": "",
    "EXTRA_LINES_TEST-3": "",
    "EXTRA_LINES_TEST-4": "",
    "_Intro-0": "很久很久之前，两个种族\n和平的统治着世界：\n人类和怪物。",
    "_Intro-1": "可有一天，人类突然\n认为怪物们有要夺取\n人类灵魂的意图。",
    "_Intro-2": "随后，人类的公主\nRazberry也失踪了。",
    "_Intro-3": "人类女王随即震怒。\n她迫使国王发动\n战争...",
    "_Intro-4": "最终，是人类\n取得了胜利。",
    "_Intro-5": "怪物被封印在了\n那深海之下。",
    "_Intro-6": "据说所有靠近了\n那座悬崖的人...\n都消失的无影无踪...",
    "_NameInit-0": "贵安...",
    "_NameInit-1": "来自我介绍一下吧？",
    "_NameInit-2": "你叫什么名字！",
    "_NameInit-3": "Имя",
    "_NameInit-4": "那么现在，\n你将对Frida负起\n责任...",
    "_NameInit-5": "你所犯下的错误...",
    "_NameInit-6": "你所导致的失败...",
    "_NameInit-7": "都将成为你的罪孽...",
    "_NameInit-8": "这孩子...",
    "_NameInit-9": "是怪物们\n最后的希望...",
    "_NameInit-10": "你准备好承担\n这份责任了吗？",
    "_NameInit-11": "那就接下\n这份重担吧...",
    "_NameInit-12": "还没准备好？",
    "_NameInit-13": "好吧，那等你准备好\n再来吧...",
    "_NameInit-14": "Имя...",
    "_NameInit-15": "欢迎你！",
    "_NameInit-16": "这个孩子一直在等待着\n你的到来！",
    "_NameInit-17": "快啊，为所有生灵带去\n希望，带给他们一个\n幸福的结局吧...",
    "_GlobalText-0": "*（拨号中...）",
    "_GlobalText-1": "*（无信号。）",
    "_GlobalText-2": "* （滴。）",
    "_GlobalText-3": "* 我背包里没地方了。",
    "_GlobalText-4": "* 我的钱不够。",
    "_GlobalText-5": "------------船夫------------",
    "_GlobalText-6": "* 嗨，我是船夫...\n* 或是船妇呢。",
    "_GlobalText-7": "* 我喜欢在这个被结界\n  包围的小世界航行。",
    "_GlobalText-8": "* 恰啦啦。\n* 要搭船吗？",
    "_GlobalText-9": "* 好吧，有缘再见。\n* 也可能无缘？天知道。\n* 恰啦啦。",
    "_GlobalText-10": "* 恰啦啦。\n* 向着冒险出发！",
    "_GlobalText-11": "* 下次再来哦。\n* 恰啦啦。",
    "_GlobalText-12": "* 咳咳...",
    "_GlobalText-13": "* 啊... 哇！！！",
    "_GlobalText-14": "* 居然有人给这个\n  号码打电话？",
    "_GlobalText-15": "* 真... 难以置信！",
    "_GlobalText-16": "* 那我就给你个\n  神秘任务。",
    "_GlobalText-17": "* 你肯定想问：\n  “为什么说是\n   秘密呢？”",
    "_GlobalText-18": "* 因为除了你，\n  从没人打过\n  这个电话。",
    "_GlobalText-19": "* 所以...\n  如果感兴趣...",
    "_GlobalText-20": "* 去紫色的灌木丛里\n  找下一封信吧！",
    "_GlobalText-21": "* 祝寻宝愉快！",
    "_GlobalText-22": "* ... ... ...",
    "_GlobalText-23": "* --- --- ---",
    "_GlobalText-24": "* 哦，嗨，Frida！",
    "_GlobalText-25": "* 近况如何？\n* 一切顺利吗？",
    "_GlobalText-26": "* 嗯，一切顺利。",
    "_GlobalText-27": "* 你...\n  是想问什么吗？",
    "_GlobalText-28": "* 没有啊，\n  就闲聊而已嘛。",
    "_GlobalText-29": "* 你那边过得如何？",
    "_GlobalText-30": "* 哈哈！\n  多谢关心。",
    "_GlobalText-31": "* 一切顺利。",
    "_GlobalText-32": "* 就是得搞点材料，\n  前些日子让我\n  用光了。",
    "_GlobalText-33": "* 什么材料？",
    "_GlobalText-34": "* 啊...\n  倒没啥特别的...",
    "_GlobalText-35": "* 是惊喜哦！",
    "_GlobalText-36": "* 哦...\n  好吧！",
    "_GlobalText-37": "* 好，最后一个！",
    "_GlobalText-38": "* 现在不方便说话，\n  请稍等一会。",
    "_GlobalText-39": "* 好吗，Frida？",
    "_GlobalText-40": "* 好的。",
    "_GlobalText-41": "* 注意安全！",
    "_GlobalText-42": "* 嗨！亲爱的！",
    "_GlobalText-43": "* 说实话，你每次给我\n  打电话我都很高兴！",
    "_GlobalText-44": "* 你真的很贴心。",
    "_GlobalText-45": "* 嘿嘿。",
    "_GlobalText-46": "* 既然聊上了，\n  有件事想问你。",
    "_GlobalText-47": "* 你喜欢派吗？",
    "_GlobalText-48": "* 啊，我还挺喜欢的...",
    "_GlobalText-49": "* 特别是甜口的。",
    "_GlobalText-50": "* 好孩子！\n* 希望你能喜欢\n  我的惊喜。",
    "_GlobalText-51": "* 什么惊喜？",
    "_GlobalText-52": "* 好吃的惊喜！",
    "_GlobalText-53": "* 唔...\n* 好期待！",
    "_GlobalText-54": "* 啊，Asriel来了。",
    "_GlobalText-55": "* 我去看看他。",
    "_GlobalText-56": "* 别乱跑哦！",
    "_GlobalText-57": "* 知道啦！",
    "_GlobalText-58": "* 嗨，Frida！\n* 进展如何？",
    "_GlobalText-59": "* 一切正常。",
    "_GlobalText-60": "* 太好了！",
    "_GlobalText-61": "* 我有件事想问你...",
    "_GlobalText-62": "* 什么？\n* 请讲！",
    "_GlobalText-63": "* 我该怎样才能回家？",
    "_GlobalText-64": "* 回...家？",
    "_GlobalText-65": "* 遗迹...\n* 遗迹就是你的家啊...",
    "_GlobalText-66": "* 可...",
    "_GlobalText-67": "* 待会再说吧。",
    "_GlobalText-68": "* 好吧...",
    "_GlobalText-69": "* 你好啊，我的孩子！",
    "_GlobalText-70": "* 抱歉，手机快没电了...",
    "_GlobalText-71": "* 先不聊了。",
    "_GlobalText-72": "* 回来之后我们再\n  好好聊。",
    "_GlobalText-73": "* 好吧...",
    "_GlobalText-74": "* ..........................",
    "_ItemName-0": "",
    "_ItemName-1": "",
    "_ItemName-2": "",
    "_ItemName-3": "",
    "_ItemName-4": "",
    "_ItemName-5": "",
    "_ItemName-6": "",
    "_ItemName-7": "",
    "_ItemName-8": "",
    "_ItemName-9": "",
    "_ItemName-10": "",
    "_ItemName-11": "",
    "_ItemName-12": "",
    "_ItemName-13": "",
    "_ItemName-14": "",
    "_ItemName-15": "",
    "_ItemName-16": "",
    "_ItemName-17": "",
    "_ItemName-18": "",
    "_ItemName-19": "",
    "_ItemName-20": "",
    "_ItemName-21": "",
    "_ItemName-22": "",
    "_ItemName-23": "",
    "_ItemName-24": "",
    "_ItemName-25": "",
    "_ItemName-26": "",
    "_ItemName-27": "",
    "_ItemName-28": "",
    "_ItemName-29": "",
    "_ItemName-30": "",
    "_ItemName-31": "",
    "_ItemName-32": "",
    "_ItemName-33": "",
    "_ItemName-34": "",
    "_ItemName-35": "",
    "_ItemName-36": "",
    "_ItemName-37": "",
    "_ItemName-38": "",
    "_ItemName-39": "",
    "_ItemName-40": "",
    "_ItemName-41": "",
    "_ItemName-42": "",
    "_ItemName-43": "",
    "_ItemName-44": "",
    "_ItemNameBattle-0": "",
    "_ItemNameBattle-1": "",
    "_ItemNameBattle-2": "",
    "_ItemNameBattle-3": "",
    "_ItemNameBattle-4": "",
    "_ItemNameBattle-5": "",
    "_ItemNameBattle-6": "",
    "_ItemNameBattle-7": "",
    "_ItemNameBattle-8": "",
    "_ItemNameBattle-9": "",
    "_ItemNameBattle-10": "",
    "_ItemNameBattle-11": "",
    "_ItemNameBattle-12": "",
    "_ItemNameBattle-13": "",
    "_ItemNameBattle-14": "",
    "_ItemNameBattle-15": "",
    "_ItemNameBattle-16": "",
    "_ItemNameBattle-17": "",
    "_ItemNameBattle-18": "",
    "_ItemNameBattle-19": "",
    "_ItemNameBattle-20": "",
    "_ItemNameBattle-21": "",
    "_ItemNameBattle-22": "",
    "_ItemNameBattle-23": "",
    "_ItemNameBattle-24": "",
    "_ItemNameBattle-25": "",
    "_ItemNameBattle-26": "",
    "_ItemNameBattle-27": "",
    "_ItemNameBattle-28": "",
    "_ItemNameBattle-29": "",
    "_ItemNameBattle-30": "",
    "_ItemNameBattle-31": "",
    "_ItemNameBattle-32": "",
    "_ItemNameBattle-33": "",
    "_ItemNameBattle-34": "",
    "_ItemNameBattle-35": "",
    "_ItemNameBattle-36": "",
    "_ItemNameBattle-37": "",
    "_ItemNameBattle-38": "",
    "_ItemNameBattle-39": "",
    "_ItemNameBattle-40": "",
    "_ItemNameBattle-41": "",
    "_ItemNameBattle-42": "",
    "_ItemNameBattle-43": "",
    "_ItemNameBattle-44": "",
    "_ItemUse-0": "",
    "_ItemUse-1": "",
    "_ItemUse-2": "",
    "_ItemUse-3": "",
    "_ItemUse-4": "",
    "_ItemUse-5": "",
    "_ItemUse-6": "",
    "_ItemUse-7": "",
    "_ItemUse-8": "",
    "_ItemUse-9": "",
    "_ItemUse-10": "",
    "_ItemUse-11": "",
    "_ItemUse-12": "",
    "_ItemUse-13": "",
    "_ItemUse-14": "",
    "_ItemUse-15": "",
    "_ItemUse-16": "",
    "_ItemUse-17": "",
    "_ItemUse-18": "",
    "_ItemUse-19": "",
    "_ItemUse-20": "",
    "_ItemUse-21": "",
    "_ItemUse-22": "",
    "_ItemUse-23": "",
    "_ItemUse-24": "",
    "_ItemUse-25": "",
    "_ItemUse-26": "",
    "_ItemUse-27": "",
    "_ItemUse-28": "",
    "_ItemUse-29": "",
    "_ItemUse-30": "",
    "_ItemUse-31": "",
    "_ItemUse-32": "",
    "_ItemUse-33": "",
    "_ItemUse-34": "",
    "_ItemUse-35": "",
    "_ItemUse-36": "",
    "_ItemUse-37": "",
    "_ItemUse-38": "",
    "_ItemUse-39": "",
    "_ItemUse-40": "",
    "_ItemUse-41": "",
    "_ItemUse-42": "",
    "_ItemUse-43": "",
    "_ItemInfo-0": "",
    "_ItemInfo-1": "",
    "_ItemInfo-2": "",
    "_ItemInfo-3": "",
    "_ItemInfo-4": "",
    "_ItemInfo-5": "",
    "_ItemInfo-6": "",
    "_ItemInfo-7": "",
    "_ItemInfo-8": "",
    "_ItemInfo-9": "",
    "_ItemInfo-10": "",
    "_ItemInfo-11": "",
    "_ItemInfo-12": "",
    "_ItemInfo-13": "",
    "_ItemInfo-14": "",
    "_ItemInfo-15": "",
    "_ItemInfo-16": "",
    "_ItemInfo-17": "",
    "_ItemInfo-18": "",
    "_ItemInfo-19": "",
    "_ItemInfo-20": "",
    "_ItemInfo-21": "",
    "_ItemInfo-22": "",
    "_ItemInfo-23": "",
    "_ItemInfo-24": "",
    "_ItemInfo-25": "",
    "_ItemInfo-26": "",
    "_ItemInfo-27": "",
    "_ItemInfo-28": "",
    "_ItemInfo-29": "",
    "_ItemInfo-30": "",
    "_ItemInfo-31": "",
    "_ItemInfo-32": "",
    "_ItemInfo-33": "",
    "_ItemInfo-34": "",
    "_ItemInfo-35": "",
    "_ItemInfo-36": "",
    "_ItemInfo-37": "",
    "_ItemInfo-38": "",
    "_ItemInfo-39": "",
    "_ItemInfo-40": "",
    "_ItemInfo-41": "",
    "_ItemInfo-42": "",
    "_ItemInfo-43": "",
    "_ItemInfo-44": "",
    "ItemDrop-0": "",
    "ItemDrop-1": "",
    "ItemDrop-2": "",
    "ItemDrop-3": "",
    "ItemDrop-4": "",
    "ItemDrop-5": "",
    "ItemDrop-6": "",
    "ItemDrop-7": "",
    "ItemDrop-8": "",
    "ItemDrop-9": "",
    "ItemDrop-10": "",
    "ItemDrop-11": "",
    "ItemDrop-12": "",
    "ItemDrop-13": "",
    "ItemDrop-14": "",
    "ItemDrop-15": "",
    "ItemDrop-16": "",
    "_RoomNames-0": "",
    "_RoomNames-1": "",
    "_RoomNames-2": "",
    "_RoomNames-3": "",
    "_RoomNames-4": "",
    "_RoomNames-5": "",
    "_RoomNames-6": "",
    "_RoomNames-7": "",
    "_RoomNames-8": "",
    "_RoomNames-9": "",
    "_RoomNames-10": "",
    "_RoomNames-11": "",
    "_RoomNames-12": "",
    "_RoomNames-13": "",
    "_RoomNames-14": "",
    "_RoomNames-15": "",
    "_RoomNames-16": "",
    "_RoomNames-17": "",
    "_RoomNames-18": "",
    "_RoomNames-19": "",
    "_RoomNames-20": "",
    "_RoomNames-21": "",
    "_RoomNames-22": "",
    "room_surface-0": "* 一切都好奇怪...",
    "room_surface-1": "* 这不可能啊...",
    "room_surface-2": "* 怎么会有人就那样\n  掉下悬崖呢！\n* 我才不信呢！",
    "room_surface-3": "* 是因为那个悬崖很特殊吗？",
    "room_surface-4": "* 我...我一定要亲自去\n  调查清楚！",
    "room_surface-5": "* 嘿，Frida，\n  你还没睡？",
    "room_surface-6": "* 是啊...",
    "room_surface-7": "* 还想吃点夜宵吗？",
    "room_surface-8": "* 不用了。",
    "room_surface-9": "* 行。",
    "room_surface-10": "* 如果有什么事的话，\n  来我房间找我就行。",
    "room_surface-11": "* 我知道了。",
    "room_surface-12": "* 这个沙发很软。",
    "room_surface-13": "* 坐上去非常舒服。",
    "room_surface-14": "* 我喜欢这个冰箱。",
    "room_surface-15": "* 不过，它总是空的。",
    "room_surface-16": "* 这是千层面吗？",
    "room_surface-17": "* 真的好硬...",
    "room_surface-18": "* 这真的还是千层面吗？",
    "room_surface-19": "* 管它呢，我可要带上。",
    "room_surface-20": "* 我得到了巨硬千层面。",
    "room_surface-21": "* 这是我的爸爸。",
    "room_surface-22": "* Frida，有什么事吗？",
    "room_surface-23": "* 没事。",
    "room_surface-24": "* 你看上去很困了...",
    "room_surface-25": "* 不如你先去睡吧？",
    "room_surface-26": "* 好吧...",
    "room_surface-27": "* 晚安，爱你哦。",
    "room_surface-28": "* 这是我的床。",
    "room_surface-29": "* 又软又舒服。",
    "room_surface-30": "* 我的衣柜里面全都是衣服。",
    "room_surface-31": "* 我的妈妈是个设计师，\n  她给我做了很多很酷的衣服。",
    "room_surface-32": "* 但是她现在在国外出差...",
    "room_surface-33": "* 我很想她。",
    "room_surface-34": "* 这是我写作业用的书桌。",
    "room_surface-35": "* 我在电脑里面写了很多故事。",
    "room_surface-36": "* 但只有我的网友\n  会喜欢它们...",
    "room_surface-37": "* 而且我们可能\n  永远见不到面。",
    "room_surface-38": "* 我喜欢读书。",
    "room_surface-39": "* 等等...我记得这里还有\n  一本我没看完的书的。",
    "room_surface-40": "* 它上哪去了？",
    "room_surface-41": "* 我的梦想书架，\n  里面都是有趣的书。",
    "room_surface-42": "* 一株植物。",
    "room_surface-43": "* 它长得像小麦，\n  但却是红色的。",
    "room_surface-44": "* 这个壁炉在冬天会很暖和。",
    "room_surface-45": "* 这台电视平时很少看。",
    "room_surface-46": "* 爸爸妈妈的床。",
    "room_surface-47": "* 哦，这是我送给妈妈\n  作为生日礼物的画。",
    "room_surface-48": "* 我的浴室。",
    "room_surface-49": "* 泡泡浴，还有温水...",
    "room_surface-50": "* 有时候比温泉还要舒服。",
    "room_surface-51": "* 这个水池很高。",
    "room_surface-52": "* 这是燃气炉。",
    "room_surface-53": "* 爸爸不让我靠近它，\n  更别说打开它了。",
    "room_surface-54": "* 他说那很危险。",
    "room_surface-55": "* 切菜用的案板。",
    "room_surface-56": "* 这里放着很多餐具。",
    "room_surface-57": "* 这里是放防热手套的圣地。",
    "room_surface-58": "* 这是我们吃饭用的餐桌。",
    "room_surface-59": "* 我还记得当时的聊天。",
    "room_surface-60": "* 我真希望妈妈能快点回来。",
    "room_surface-61": "* 他现在在国外呢。",
    "room_surface-62": "* 我爱我的家人！",
    "room_surface-63": "* 很多工具。",
    "room_surface-64": "* 用来洗菜洗碗的水池。",
    "room_surface-65": "* 有一次，我不小心把妈妈的\n  一个首饰给掉进去了。",
    "room_surface-66": "* 如果我现在出门，\n  可能很久都不会回来。",
    "room_surface-67": "* （开始冒险吗？）\n\n        出发         再想想",
    "room_surface-68": "* 没有回头路了...",
    "room_surface-69": "* 一篇寻童启事。",
    "room_surface-70": "* 看上去有些年份了...\n* 至少有十年了吧...\n* 也可能更久...",
    "room_surface-71": "* 一切看上去都很正常...",
    "room_surface-72": "* 那为什么还会有人\n  在这里失踪？",
    "room_surface-73": "* 美丽的森林。\n* 它有什么不对吗？",
    "room_surface-74": "* 这就是悬崖了！",
    "room_surface-75": "* 多美的景色啊！",
    "room_surface-76": "* 我都能看到远处\n  城市的灯光了...",
    "room_surface-77": "* 那是什么？",
    "room_ruin_start-0": "* 我落到了这些花上。",
    "room_ruin_start-1": "",
    "room_ruin_start-2": "* 我从书上读到过，\n  这些花可以让人在水下呼吸！",
    "room_ruin_start-3": "* 哇哦！这也太神奇了！",
    "room_ruin_start-4": "",
    "room_ruin_start-5": "* 它们可以让人在水下呼吸。",
    "room_ruin_start-6": "* 发生什么了？",
    "room_ruin_start-7": "* 别担心我，孩子...",
    "room_ruin_start-8": "* 继续前进吧...",
    "room_ruin_start-9": "* 不要停下脚步...",
    "room_ruin_corally-0": "",
    "room_ruin_corally-1": "* 嗯...",
    "room_ruin_corally-2": "* 你才刚来到这片海域，对吧？",
    "room_ruin_corally-3": "* 天哪噜，\n  那你一定迷路了吧。",
    "room_ruin_corally-4": "* 得有人帮你搞清楚\n  这里的状况！",
    "room_ruin_corally-5": "* 显而易见，\n  那个人就是我啦！",
    "room_ruin_corally-6": "* 准备好了吗？\n* 我们开始吧！",
    "room_ruin_corally-7": "* 你没有更好的事要做了吗？",
    "room_ruin_corally-8": "* 开始吧！",
    "room_ruin1-0": "* 坠落于海底后，\n  我已准备好培养耐心...",
    "room_ruin1-1": "* ...只为能离开此地...",
    "room_ruin1-2": "* 一个头巾。",
    "room_ruin1-3": "* 拿上头巾吗？\n\n        拿         不拿",
    "room_ruin1-4": "* 我拿上了头巾。",
    "room_ruin1-5": "* 我装不下了！",
    "room_ruin2-0": "* 欢迎来到遗迹，这里现在\n  是你的新家了，孩子！",
    "room_ruin2-1": "* 额...\n  一直这样叫你\n  总感觉有点不太礼貌...",
    "room_ruin2-2": "* 亲爱的孩子...\n* 你可以... 告诉我你的名字吗？",
    "room_ruin2-3": "* 我叫... Frida...",
    "room_ruin2-4": "* Frida？\n  多可爱的名字啊！",
    "room_ruin2-5": "* 那... 接着说！",
    "room_ruin2-6": "* 就像刚才讲的那样，\n  这里现在是你的新家了，Frida！",
    "room_ruin2-7": "* 海底遗迹中到处都是谜题。",
    "room_ruin2-8": "* 来试着自己解决这一个吧！",
    "room_ruin2-9": "* 你只需要\n  按下三个开关就行了。",
    "room_ruin2-10": "* 要是没有头绪，\n  可以去找找这附近的\n  一个线索。",
    "room_ruin2-11": "* 祝你好运！",
    "room_ruin2-12": "* 干得好！\n  我们去下一个房间吧。",
    "room_ruin2-13": "* 1\n  0\n  1\n  1",
    "room_ruin2-14": "* 这一定就是线索了！",
    "room_ruin3-0": "* 哦，这水晶又放错位置了？",
    "room_ruin3-1": "* 要想继续前行，\n  我们需要把水晶推出来\n  才能通过这里。",
    "room_ruin3-2": "* 但现在，\n  它周围却布满了尖刺。",
    "room_ruin3-3": "* 所以得先把尖刺解除才行。",
    "room_ruin3-4": "* 我相信你可以只靠自己\n  来解决这个谜题。",
    "room_ruin3-5": "* 来吧，\n  这并没有那么难。",
    "room_ruin3-6": "* 跑得快一点就可以了。",
    "room_ruin3-7": "* 还有就是...",
    "room_ruin3-8": "* 要小心一点！",
    "room_ruin3-9": "* 再快一点！\n* 下次肯定能过！",
    "room_ruin3-10": "* 干得好！你真的太棒了！",
    "room_ruin3-11": "* 现在去推一下那块水晶！",
    "room_ruin3-12": "* 恭喜你！\n  只靠自己就解决了谜题！",
    "room_ruin3-13": "* 我们去下一个房间吧。",
    "room_ruin3-14": "* 上面写着：\n  “警告！\n   小心跌入悬崖！”",
    "room_ruin_dummy-0": "* 你要知道...",
    "room_ruin_dummy-1": "* 在海洋里，\n  存在着不少可能会伤害\n  到你的怪物。",
    "room_ruin_dummy-2": "* 你需要为此做好准备。",
    "room_ruin_dummy-3": "* 去和这个人偶练习一下吧！",
    "room_ruin_dummy-4": "* 每一种怪物都需要以\n  不同的方法来应对。",
    "room_ruin_dummy-5": "* 这个人偶看起来像一条鱼！",
    "room_ruin_dummy-6": "* 你好？",
    "room_ruin_dummy-7": "* 嗯... 下次可以试试在\n  不动手的情况下解决问题吗？",
    "room_ruin_dummy-8": "* 你在跟他聊天吗？\n  看来你交到了一个新朋友呢。",
    "room_ruin_dummy-9": "* 通常情况下，\n  饶恕你的敌人往往是个\n  不错的选择。",
    "room_ruin_dummy-10": "* 但要记住...",
    "room_ruin_dummy-11": "* ...有些怪物在一开始\n  是不能被饶恕的。",
    "room_ruin_dummy-12": "* ...你是不是逃跑了？\n* 好吧，其实也还不错。",
    "room_ruin_dummy-13": "* 但你无法逃避一切，\n  终有一天你会需要直面困难。",
    "room_ruin_dummy-14": "* 好了，\n  我们结束这个课程吧。",
    "room_ruin_dummy-15": "* 下个房间也有一个谜题。",
    "room_ruin_dummy-16": "* 但你可以自己解决吗？",
    "room_ruin_dummy-17": "* 实在不好意思，\n  但我还有一些事得去\n  处理一下...",
    "room_ruin_dummy-18": "* 比如什么？",
    "room_ruin_dummy-19": "* 我现在还不能告诉你...\n* 这是个秘密，\n  你以后就会知道了。",
    "room_ruin_dummy-20": "* 对了，\n  我把我的号码给你。",
    "room_ruin_dummy-21": "* 要好好记住哦！",
    "room_ruin_dummy-22": "* 这样的话，\n  要是你遇到麻烦了，\n  就可以打电话找我帮忙了。",
    "room_ruin_dummy-23": "* 先失陪了，我得走了...",
    "room_ruin_dummy-24": "* 好好照顾自己！",
    "room_ruin_dummy-25": "* 来吧，\n  和这个可爱的人偶聊聊天吧！",
    "room_ruin_dummy-26": "* 友善一点吧，孩子...",
    "room_ruin_dummy-27": "* 这个人偶在平时非常孤独，\n  去和他交个朋友吧。",
    "room_ruin_dummy-28": "* 哈喽啊，小鱼！",
    "room_ruin_dummy-29": "* 啊，你还是\n  这么沉默寡言呢...",
    "room_ruin_fall-0": "* 上面写着：\n  “不要踩树叶。”",
    "room_ruin_fall-1": "* 这是一个小吃摊，\n  售卖者是三只螃蟹。",
    "room_ruin_fall-2": "* 或者说售卖三种螃蟹。",
    "room_ruin_fall-3": "* （要买什么？）\n    蟹肉可颂   朗姆酒\n    蟹肉棒    算了",
    "room_ruin_fall-4": "* 我要花15$买一份蟹肉可颂吗？\n        买         不买",
    "room_ruin_fall-5": "* 现在我得到了一个蟹肉可颂。",
    "room_ruin_fall-6": "* 我要花25$买一瓶朗姆酒吗？\n        买         不买",
    "room_ruin_fall-7": "* 现在我获得了一瓶朗姆酒。",
    "room_ruin_fall-8": "* 我要花20$买一份蟹肉棒吗？\n        买         不买",
    "room_ruin_fall-9": "* 现在我获得了一份蟹肉棒。",
    "room_ruin_fall-10": "* 我的钱不够！",
    "room_ruin_fall-11": "* 看到那些树叶了吗？\n* 想象一下，它们会让人坠落。\n  所以千万不要踩它们！",
    "room_ruin_fall-12": "* 我没地方放了！",
    "room_ruin_fall-13": "* “请来购买我们的食品！”",
    "room_ruin_fall-14": "* “蟹做蟹卖的可颂和蟹肉棒！”\n* “蟹料十足！”",
    "room_ruin_fall-15": "* “还有沁人心脾的朗姆酒！”\n* “十分解壳！恭迎选购！”",
    "room_ruin_bench-0": "* 哇哦，好舒服的长椅啊！",
    "room_ruin_bench-1": "* 我要坐在长椅上吗？\n        坐         不坐",
    "room_ruin_bench-2": "* 真舒服。",
    "room_ruin_bench-3": "* 一把长椅。",
    "room_ruin_bench-4": "* “别迷路了！”",
    "room_ruin_bench-5": "* 这只狗一直在逃避我！\n  就像脚滑的狐狸一样！\n* 根本抓不住！",
    "room_ruin_ghost-0": "* 哦...\n  这只幽灵看起来好悲伤...",
    "room_ruin_ghost-1": "* 他也许知道\n  怎么打开这扇门。",
    "room_ruin_ghost-2": "* 要打扰他吗？\n\n        打扰         不要",
    "room_ruin_ghost-3": "* 这扇门关着。\n* 也许这个幽灵知道\n  怎么打开它。",
    "room_ruin_ghost-4": "* 感谢你所做的一切...",
    "room_ruin_ghost-5": "* 哦...",
    "room_ruin_tube-0": "* 哦，嗨...",
    "room_ruin_tube-1": "* 据我所知，\n  你叫Frida对吧？",
    "room_ruin_tube-2": "* 啊，是的！\n* 你好啊！",
    "room_ruin_tube-3": "* 你咋知道我的名字？",
    "room_ruin_tube-4": "* 我叫Asriel，\n  Toriel之子。",
    "room_ruin_tube-5": "* 很高兴见到你，Asriel！",
    "room_ruin_tube-6": "* 能带我去你家吗？",
    "room_ruin_tube-7": "* 我妈没告诉你要\n  待在原地吗？",
    "room_ruin_tube-8": "* 我就是感觉太无聊了...\n  想出来走走...",
    "room_ruin_tube-9": "* 啊行... \n  你可真是个急性子...",
    "room_ruin_tube-10": "* 我已经够有耐心了！",
    "room_ruin_tube-11": "* 好好好，咱走吧。",
    "room_ruin_tube-12": "* 带你解决几个谜题去。",
    "room_ruin_tube-13": "* 真的吗？太谢谢你了！",
    "room_ruin_tube-14": "* 跟我来吧，Frida。",
    "room_ruin_tiles-0": "",
    "room_ruin_tiles-1": "",
    "room_ruin_tiles-2": "",
    "room_ruin_tiles-3": "",
    "room_ruin_tiles-4": "",
    "room_ruin_tiles-5": "",
    "room_ruin_tiles-6": "",
    "room_ruin_tiles-7": "",
    "room_ruin_tiles-8": "",
    "room_ruin_tiles-9": "",
    "room_ruin_tiles-10": "",
    "room_ruin_tiles-11": "",
    "room_ruin_tiles-12": "",
    "room_ruin_tiles-13": "",
    "room_ruin_tiles-14": "",
    "room_ruin_tiles-15": "",
    "room_ruin_tiles-16": "",
    "room_ruin_longpuzzle-0": "",
    "room_ruin_longpuzzle-1": "",
    "room_ruin_longpuzzle-2": "",
    "room_ruin_longpuzzle-3": "",
    "room_ruin_longpuzzle-4": "",
    "room_ruin_longpuzzle-5": "",
    "room_ruin_longpuzzle-6": "",
    "room_ruin_longpuzzle-7": "",
    "room_ruin_longpuzzle-8": "",
    "room_ruin_longpuzzle-9": "",
    "room_ruin_longpuzzle-10": "* 我知道了。",
    "room_ruin_longpuzzle-11": "",
    "room_ruin_longpuzzle-12": "",
    "room_ruin_longpuzzle-13": "",
    "room_ruin_longpuzzle-14": "",
    "room_ruin_longpuzzle-15": "",
    "room_ruin_longpuzzle-16": "",
    "room_ruin_longpuzzle-17": "",
    "room_ruin_longpuzzle-18": "",
    "room_ruin_longpuzzle-19": "",
    "room_ruin_longpuzzle-20": "",
    "room_ruin_longpuzzle-21": "",
    "room_ruin_longpuzzle-22": "",
    "room_ruin_longpuzzle-23": "",
    "room_ruin_longpuzzle-24": "",
    "room_ruin_longpuzzle-25": "",
    "room_ruin_longpuzzle-26": "",
    "room_ruin_longpuzzle-27": "",
    "room_ruin_longpuzzle-28": "",
    "room_ruin_longpuzzle-29": "",
    "room_ruin_longpuzzle-30": "",
    "room_ruin_longpuzzle-31": "",
    "room_ruin_longpuzzle-32": "",
    "room_ruin_longpuzzle-33": "",
    "room_ruin_longpuzzle-34": "",
    "room_ruin_longpuzzle-35": "",
    "room_ruin_longpuzzle-36": "",
    "room_ruin_longpuzzle-37": "",
    "room_ruin_longpuzzle-38": "",
    "room_ruin_longpuzzle-39": "",
    "room_ruin_longpuzzle-40": "",
    "room_ruin_longpuzzle-41": "",
    "room_ruin_longpuzzle-42": "",
    "room_ruin_rock-0": "",
    "room_ruin_rock-1": "",
    "room_ruin_rock-2": "",
    "room_ruin_rock-3": "",
    "room_ruin_rock-4": "",
    "room_ruin_rock-5": "",
    "room_ruin_rock-6": "",
    "room_ruin_rock-7": "",
    "room_ruin_rock2-0": "",
    "room_ruin_rock2-1": "",
    "room_ruin_rock2-2": "",
    "room_ruin_rock2-3": "",
    "room_ruin_rock2-4": "",
    "room_ruin_rock2-5": "",
    "room_ruin_gardenA-0": "",
    "room_ruin_gardenA-1": "",
    "room_ruin_gardenA-2": "",
    "room_ruin_gardenA-3": "",
    "room_ruin_gardenA-4": "",
    "room_ruin_gardenA-5": "",
    "room_ruin_gardenA-6": "",
    "room_ruin_gardenB-0": "",
    "room_ruin_gardenB-1": "",
    "room_ruin_gardenB-2": "",
    "room_ruin_gardenB-3": "",
    "room_ruin_gardenB-4": "",
    "room_ruin_gardenB-5": "",
    "room_ruin_gardenB-6": "",
    "room_ruin_gardenB-7": "",
    "room_ruin_gardenB-8": "",
    "room_ruin_gardenB-9": "",
    "room_ruin_gardenB-10": "",
    "room_ruin_gardenB-11": "",
    "room_ruin_gardenB-12": "",
    "room_ruin_house-0": "",
    "room_ruin_house-1": "",
    "room_ruin_house-2": "",
    "room_ruin_house-3": "",
    "room_toriel_house-0": "",
    "room_toriel_house-1": "",
    "room_toriel_house-2": "",
    "room_toriel_house-3": "",
    "room_toriel_house-4": "",
    "room_toriel_house-5": "",
    "room_toriel_house-6": "",
    "room_toriel_house-7": "",
    "room_toriel_house-8": "",
    "room_toriel_house-9": "",
    "room_toriel_house-10": "",
    "room_toriel_house-11": "",
    "room_toriel_house-12": "",
    "room_toriel_house-13": "",
    "room_toriel_house-14": "",
    "room_toriel_house-15": "",
    "room_toriel_house-16": "",
    "room_toriel_house-17": "",
    "room_toriel_house-18": "",
    "room_toriel_house-19": "",
    "room_toriel_house-20": "* 这是我的床。",
    "room_toriel_house-21": "",
    "room_toriel_house-22": "",
    "room_toriel_house-23": "",
    "room_toriel_house-24": "",
    "room_toriel_house-25": "",
    "room_toriel_house-26": "",
    "room_toriel_house-27": "",
    "room_toriel_house-28": "",
    "room_toriel_house-29": "",
    "room_toriel_house-30": "",
    "room_toriel_house-31": "",
    "room_toriel_house-32": "",
    "room_toriel_house-33": "",
    "room_toriel_house-34": "",
    "room_toriel_house-35": "",
    "room_toriel_house-36": "",
    "room_toriel_house-37": "",
    "room_toriel_house-38": "",
    "room_toriel_house-39": "",
    "room_toriel_house-40": "",
    "room_toriel_house-41": "",
    "room_toriel_house-42": "",
    "room_toriel_house-43": "",
    "room_toriel_house-44": "",
    "room_toriel_house-45": "",
    "room_toriel_house-46": "",
    "room_toriel_house-47": "",
    "room_toriel_house-48": "",
    "room_toriel_house-49": "",
    "room_toriel_house-50": "",
    "room_toriel_house-51": "",
    "room_toriel_house-52": "",
    "room_toriel_house-53": "",
    "room_toriel_house-54": "",
    "room_toriel_house-55": "",
    "room_toriel_house-56": "",
    "room_toriel_house-57": "",
    "room_toriel_house-58": "",
    "room_toriel_house-59": "",
    "room_toriel_house-60": "",
    "room_toriel_house-61": "",
    "room_toriel_house-62": "",
    "room_toriel_house-63": "",
    "room_toriel_house-64": "",
    "room_toriel_house-65": "",
    "room_toriel_house-66": "",
    "room_toriel_house-67": "",
    "room_toriel_house-68": "",
    "room_toriel_house-69": "",
    "room_toriel_house-70": "",
    "room_toriel_house-71": "",
    "room_toriel_house-72": "",
    "room_toriel_house-73": "",
    "room_toriel_house-74": "",
    "room_toriel_house-75": "",
    "room_toriel_house-76": "",
    "room_toriel_house-77": "",
    "room_toriel_house-78": "",
    "room_toriel_house-79": "* 我知道了。",
    "room_toriel_house-80": "",
    "room_toriel_house-81": "",
    "room_toriel_house-82": "",
    "room_toriel_house-83": "",
    "room_toriel_house-84": "",
    "room_toriel_house-85": "",
    "room_toriel_house-86": "",
    "room_toriel_house-87": "",
    "room_toriel_house-88": "",
    "room_toriel_house-89": "",
    "room_toriel_house-90": "",
    "room_toriel_house-91": "",
    "room_toriel_house-92": "",
    "room_toriel_house-93": "",
    "room_toriel_house-94": "",
    "room_toriel_house-95": "",
    "room_toriel_house-96": "",
    "room_toriel_house-97": "",
    "room_toriel_house-98": "",
    "room_toriel_house-99": "",
    "room_toriel_house-100": "",
    "room_toriel_house-101": "",
    "room_toriel_house-102": "",
    "room_toriel_house-103": "",
    "room_toriel_house-104": "",
    "room_toriel_house-105": "",
    "room_toriel_house-106": "",
    "room_toriel_house-107": "",
    "room_toriel_house-108": "",
    "room_toriel_house-109": "",
    "room_toriel_house-110": "",
    "room_toriel_house-111": "",
    "room_toriel_house-112": "",
    "room_toriel_house-113": "",
    "room_toriel_house-114": "",
    "room_toriel_house-115": "",
    "room_toriel_house-116": "",
    "room_toriel_house-117": "",
    "room_toriel_house-118": "",
    "room_toriel_house-119": "* 很多工具。",
    "room_toriel_house-120": "",
    "room_toriel_house-121": "",
    "room_toriel_house-122": "",
    "room_toriel_house-123": "",
    "room_toriel_house-124": "",
    "room_toriel_house-125": "",
    "room_toriel_house-126": "",
    "room_toriel_house-127": "",
    "room_toriel_house-128": "",
    "room_toriel_house-129": "",
    "room_toriel_house-130": "",
    "room_toriel_house-131": "",
    "room_toriel_house-132": "",
    "room_toriel_house-133": "",
    "room_toriel_house-134": "",
    "room_toriel_house-135": "",
    "room_toriel_house-136": "",
    "room_toriel_house-137": "",
    "room_toriel_house-138": "",
    "room_ruin_exit-0": "",
    "room_ruin_exit-1": "",
    "room_ruin_exit-2": "",
    "room_ruin_exit-3": "",
    "room_ruin_exit-4": "",
    "room_ruin_exit-5": "",
    "room_ruin_exit-6": "",
    "room_ruin_exit-7": "",
    "room_ruin_exit-8": "",
    "room_ruin_exit-9": "",
    "room_ruin_exit-10": "",
    "room_ruin_exit-11": "",
    "room_ruin_exit-12": "",
    "room_ruin_exit-13": "",
    "room_ruin_exit-14": "",
    "room_ruin_exit-15": "",
    "room_ruin_exit-16": "",
    "room_ruin_exit-17": "",
    "room_ruin_exit-18": "",
    "room_ruin_exit-19": "",
    "room_ruin_exit-20": "",
    "room_ruin_exit-21": "",
    "room_ruin_exit-22": "",
    "room_ruin_exit-23": "",
    "room_ruin_exit-24": "",
    "room_ruin_exit-25": "",
    "room_ruin_exit-26": "",
    "room_ruin_exit-27": "",
    "room_ruin_exit-28": "",
    "room_ruin_exit-29": "",
    "room_ruin_exit-30": "",
    "room_ruin_exit-31": "",
    "room_ruin_exit-32": "",
    "room_ruin_exit-33": "",
    "room_ruin_exit-34": "",
    "room_ruin_exit-35": "",
    "room_ruin_exit-36": "",
    "room_ruin_exit-37": "",
    "room_ruin_exit-38": "",
    "room_ruin_exit-39": "",
    "room_ruin_exit-40": "",
    "room_ruin_exit-41": "",
    "room_ruin_exit-42": "",
    "room_ruin_exit-43": "",
    "room_ruin_exit-44": "",
    "room_ruin_exit-45": "",
    "room_ruin_exit-46": "",
    "room_ruin_exit-47": "",
    "room_ruin_exit-48": "",
    "room_sandin-0": "",
    "room_sandin-1": "",
    "room_sandin-2": "",
    "room_sandin-3": "",
    "room_sandin-4": "",
    "room_sandin-5": "",
    "room_sandin-6": "",
    "room_sandin-7": "",
    "room_sandin-8": "",
    "room_sandin-9": "",
    "room_sandin-10": "",
    "room_sandin-11": "",
    "room_sandin-12": "",
    "room_sandin-13": "",
    "room_sandin-14": "",
    "room_sandin-15": "",
    "room_sandin-16": "",
    "room_sandin-17": "",
    "room_sandin-18": "",
    "room_sandin-19": "",
    "room_sandin-20": "",
    "room_sandin-21": "",
    "room_sandin-22": "",
    "room_sandin-23": "",
    "room_sandin-24": "",
    "room_sandin-25": "",
    "room_sandin-26": "",
    "room_sandin-27": "",
    "room_sandin-28": "",
    "room_sandin-29": "",
    "room_sandin-30": "",
    "room_sandin-31": "",
    "room_sandin-32": "",
    "room_sandin-33": "",
    "room_sandin-34": "",
    "room_sandin-35": "",
    "room_sandin-36": "",
    "room_sandin-37": "",
    "room_sandin-38": "",
    "room_sandin-39": "",
    "room_sandin-40": "",
    "room_sandin-41": "",
    "room_sandin-42": "",
    "room_sandin-43": "",
    "room_sandin-44": "",
    "room_sandin-45": "",
    "room_sandin-46": "",
    "room_sandin-47": "",
    "room_sandin-48": "",
    "room_sandin-49": "",
    "room_sandin-50": "",
    "room_sandin_boat-0": "",
    "room_sandin_boat-1": "",
    "room_sandin_boat-2": "",
    "room_sandin_boat-3": "",
    "room_sandin_boat-4": "",
    "room_sandin_boat-5": "",
    "room_sandin_boat-6": "",
    "room_sandin_boat-7": "",
    "room_sandin_boat-8": "",
    "room_sandin_boat-9": "",
    "room_sandin_boat-10": "",
    "room_sandin_boat-11": "",
    "room_sandin_boat-12": "",
    "room_sandin_boat-13": "",
    "room_sandin_boat-14": "",
    "room_sandin_boat-15": "",
    "room_sandin_boat-16": "",
    "room_sandin_boat-17": "",
    "room_sandin_boat-18": "",
    "room_sandin_boat-19": "",
    "room_sandin_boat-20": "",
    "room_sandin_boat-21": "",
    "room_sandin_boat-22": "",
    "room_sandin_boat-23": "",
    "room_sandin_boat-24": "",
    "room_sandin_boat-25": "",
    "room_sandin_boat-26": "",
    "room_sandin_boat-27": "",
    "room_sandin_boat-28": "",
    "room_sandin_doggo-0": "",
    "room_sandin_doggo-1": "",
    "room_sandin_doggo-2": "",
    "room_sandin_doggo-3": "",
    "room_sandin_doggo-4": "",
    "room_sandin_doggo-5": "",
    "room_sandin_doggo-6": "",
    "room_sandin_doggo-7": "",
    "room_sandin_raspberry-0": "",
    "room_sandin_raspberry-1": "",
    "room_sandin_raspberry-2": "",
    "room_sandin_raspberry-3": "",
    "room_sandin_raspberry-4": "",
    "room_sandin_raspberry-5": "",
    "room_sandin_raspberry-6": "",
    "room_sandin_raspberry-7": "",
    "room_sandin_raspberry-8": "",
    "room_sandin_raspberry-9": "",
    "room_sandin_raspberry-10": "",
    "room_sandin_raspberry-11": "",
    "room_sandin_pearls-0": "",
    "room_sandin_pearls-1": "",
    "room_sandin_pearls-2": "",
    "room_sandin_pearls-3": "",
    "room_sandin_pearls-4": "",
    "room_sandin_pearls-5": "",
    "room_sandin_pearls-6": "",
    "room_sandin_pearls-7": "",
    "room_sandin_pearls-8": "",
    "room_sandin_pearls-9": "",
    "room_sandin_pearls-10": "",
    "room_sandin_pearls-11": "",
    "room_sandin_pearls-12": "",
    "room_sandin_pearls-13": "",
    "room_sandin_pearls-14": "",
    "room_sandin_pearls-15": "",
    "room_sandin_pearls-16": "",
    "room_sandin_pearls-17": "",
    "room_sandin_shopkeeper_taco-0": "",
    "room_sandin_shopkeeper_taco-1": "",
    "room_sandin_shopkeeper_taco-2": "",
    "room_sandin_shopkeeper_taco-3": "",
    "room_sandin_shopkeeper_taco-4": "",
    "room_sandin_shopkeeper_taco-5": "",
    "room_sandin_shopkeeper_taco-6": "",
    "room_sandin_shopkeeper_taco-7": "",
    "room_sandin_shopkeeper_taco-8": "",
    "room_sandin_shopkeeper_taco-9": "",
    "room_sandin_shopkeeper_taco-10": "",
    "room_sandin_shopkeeper_taco-11": "",
    "room_jungle_1-0": "",
    "room_jungle_1-1": "",
    "room_jungle_1-2": "",
    "room_jungle_1-3": "",
    "room_jungle_1-4": "",
    "room_jungle_1-5": "",
    "room_jungle_1-6": "",
    "room_jungle_1-7": "",
    "room_jungle_2-0": "",
    "room_jungle_3-0": "",
    "room_jungle_5-0": "",
    "room_jungle_5-1": "",
    "room_jungle_5-2": "",
    "room_jungle_5-3": "",
    "room_jungle_5-4": "",
    "room_jungle_5-5": "",
    "room_jungle_5-6": "",
    "room_jungle_5-7": "",
    "room_jungle_5-8": "",
    "room_jungle_5-9": "",
    "room_jungle_5-10": "",
    "room_jungle_6-0": "",
    "room_jungle_6-1": "",
    "room_jungle_6-2": "",
    "room_jungle_6-3": "",
    "room_jungle_6-4": "",
    "room_jungle_6-5": "",
    "room_jungle_7-0": "",
    "room_sandin_note-0": "",
    "room_sandin_note-1": "",
    "room_sandin_note-2": "",
    "room_sandin_note-3": "",
    "room_sandin_note-4": "",
    "room_sandin_note-5": "",
    "room_sandin_note-6": "",
    "room_sandin_note-7": "",
    "room_sandin_note-8": "",
    "room_sandin_note-9": "",
    "room_sandin_note-10": "",
    "room_sandin_note-11": "",
    "room_sandin_note-12": "",
    "room_sandin_note-13": "",
    "room_sandin_note-14": "",
    "room_sandin_note-15": "",
    "room_sandin_note-16": "",
    "room_sandin_note-17": "",
    "room_sandin_note-18": "",
    "room_sandin_note-19": "",
    "room_sandin_note-20": "",
    "room_sandin_note-21": "",
    "room_sandin_note-22": "",
    "room_sandin_note-23": "",
    "room_sandin_note-24": "",
    "room_sandin_note-25": "",
    "room_sandin_note-26": "",
    "room_sandin_note-27": "",
    "room_sandin_salad-0": "",
    "room_sandin_salad-1": "",
    "room_sandin_salad-2": "",
    "room_sandin_salad-3": "",
    "room_sandin_salad-4": "",
    "room_sandin_salad-5": "",
    "room_sandin_salad-6": "",
    "room_sandin_salad-7": "",
    "room_sandin_salad-8": "",
    "room_sandin_salad-9": "",
    "room_sandin_salad-10": "",
    "room_sandin_salad-11": "",
    "room_sandin_salad-12": "",
    "room_sandin_salad-13": "",
    "room_sandin_salad-14": "",
    "room_sandin_salad-15": "",
    "room_sandin_salad-16": "",
    "room_sandin_dogs-0": "",
    "room_sandin_dogs-1": "",
    "room_sandin_dogs-2": "",
    "room_sandin_dogs-3": "",
    "room_sandin_dogs-4": "",
    "room_sandin_dogs-5": "",
    "room_sandin_dogs-6": "",
    "room_sandin_dogs-7": "",
    "room_sandin_dogsA-0": "",
    "room_sandin_dogsA-1": "",
    "room_sandin_dogsA-2": "",
    "room_sandin_dogsA-3": "",
    "room_sandin_dogsA-4": "",
    "room_sandin_sculptures-0": "",
    "room_sandin_sculptures-1": "",
    "room_sandin_sculptures-2": "",
    "room_sandin_sculptures-3": "",
    "room_sandin_sculptures-4": "",
    "room_sandin_sculptures-5": "",
    "room_sandin_sculptures-6": "",
    "room_sandin_sculptures-7": "",
    "room_sandin_sculptures-8": "",
    "room_sandin_sculptures-9": "",
    "room_sandin_sculptures-10": "",
    "room_sandin_xoxo-0": "",
    "room_sandin_xoxo-1": "",
    "room_sandin_xoxo-2": "",
    "room_sandin_xoxo2-0": "",
    "room_sandin_xoxo2-1": "",
    "room_sandin_xoxo2-2": "",
    "room_sandin_xoxo2-3": "",
    "room_sandin_xoxo2-4": "",
    "room_sandin_xoxo2-5": "",
    "room_sandin_xoxo2-6": "",
    "room_sandin_xoxo2-7": "",
    "room_sandin_xoxo2-8": "",
    "room_sandin_xoxo2-9": "",
    "room_sandin_xoxo2-10": "",
    "room_sandin_xoxo2-11": "",
    "room_sandin_xoxo2-12": "",
    "room_sandin_ColorTilePuzzle-0": "",
    "room_sandin_ColorTilePuzzle-1": "",
    "room_sandin_ColorTilePuzzle-2": "",
    "room_sandin_ColorTilePuzzle-3": "",
    "room_sandin_ColorTilePuzzle-4": "",
    "room_sandin_ColorTilePuzzle-5": "",
    "room_sandin_ColorTilePuzzle-6": "",
    "room_sandin_ColorTilePuzzle-7": "",
    "room_sandin_ColorTilePuzzle-8": "",
    "room_sandin_ColorTilePuzzle-9": "",
    "room_sandin_ColorTilePuzzle-10": "",
    "room_sandin_ColorTilePuzzle-11": "",
    "room_sandin_ColorTilePuzzle-12": "",
    "room_sandin_ColorTilePuzzle-13": "",
    "room_sandin_ColorTilePuzzle-14": "",
    "room_sandin_ColorTilePuzzle-15": "",
    "room_sandin_ColorTilePuzzle-16": "",
    "room_sandin_ColorTilePuzzle-17": "",
    "room_sandin_ColorTilePuzzle-18": "",
    "room_sandin_ColorTilePuzzle-19": "",
    "room_sandin_ColorTilePuzzle-20": "",
    "room_sandin_ColorTilePuzzle-21": "",
    "room_sandin_ColorTilePuzzle-22": "",
    "room_sandin_ColorTilePuzzle-23": "",
    "room_sandin_ColorTilePuzzle-24": "",
    "room_sandin_ColorTilePuzzle-25": "",
    "room_sandin_ColorTilePuzzle-26": "",
    "room_sandin_ColorTilePuzzle-27": "",
    "room_sandin_ColorTilePuzzle-28": "",
    "room_sandin_ColorTilePuzzle-29": "",
    "room_sandin_ColorTilePuzzle-30": "",
    "room_sandin_ColorTilePuzzle-31": "",
    "room_sandin_ColorTilePuzzle-32": "",
    "room_sandin_ColorTilePuzzle-33": "",
    "room_sandin_ColorTilePuzzle-34": "",
    "room_sandin_ColorTilePuzzle-35": "",
    "room_sandin_ColorTilePuzzle-36": "",
    "room_sandin_ColorTilePuzzle-37": "",
    "room_sandin_ColorTilePuzzle-38": "",
    "room_sandin_ColorTilePuzzle-39": "",
    "room_sandin_ColorTilePuzzle-40": "",
    "room_sandin_ColorTilePuzzle-41": "",
    "room_sandin_ColorTilePuzzle-42": "",
    "room_sandin_ColorTilePuzzle-43": "",
    "room_sandin_ColorTilePuzzle-44": "",
    "room_sandin_ColorTilePuzzle-45": "",
    "room_sandin_ColorTilePuzzle-46": "",
    "room_sandin_ColorTilePuzzle-47": "",
    "room_sandin_ColorTilePuzzle-48": "",
    "room_sandin_ColorTilePuzzle-49": "",
    "room_sandin_ColorTilePuzzle-50": "",
    "room_sandin_ColorTilePuzzle-51": "",
    "room_sandin_ColorTilePuzzle-52": "",
    "room_sandin_ColorTilePuzzle-53": "",
    "room_sandin_ColorTilePuzzle-54": "",
    "room_sandin_ColorTilePuzzle-55": "",
    "room_sandin_startMinigame-0": "",
    "room_sandin_startMinigame-1": "",
    "room_sandin_startMinigame-2": "",
    "room_sandin_startMinigame-3": "",
    "room_sandin_endMinigame-0": "",
    "room_sandin_endMinigame-1": "",
    "room_sandin_bigdog-0": "",
    "room_sandin_bigdog-1": "",
    "room_sandin_bigdog-2": "",
    "room_sandin_bigdog-3": "",
    "room_sandin_bigdog-4": "",
    "room_sandin_bigdog-5": "",
    "room_sandin_bigdog-6": "",
    "room_sandin_bigdog-7": "",
    "room_sandin_bigdog-8": "",
    "room_sandin_fakesun-0": "",
    "room_sandin_fakesun-1": "",
    "room_sandin_dangerpuzzle-0": "",
    "room_sandin_dangerpuzzle-1": "",
    "room_sandin_dangerpuzzle-2": "",
    "room_sandin_dangerpuzzle-3": "",
    "room_sandin_dangerpuzzle-4": "",
    "room_sandin_dangerpuzzle-5": "",
    "room_sandin_dangerpuzzle-6": "",
    "room_sandin_dangerpuzzle-7": "",
    "room_sandin_dangerpuzzle-8": "",
    "room_sandin_dangerpuzzle-9": "",
    "room_sandin_dangerpuzzle-10": "",
    "room_sandin_dangerpuzzle-11": "",
    "room_sandin_dangerpuzzle-12": "",
    "room_sandin_dangerpuzzle-13": "",
    "room_sandin_dangerpuzzle-14": "",
    "room_sandin_dangerpuzzle-15": "",
    "room_sandin_dangerpuzzle-16": "",
    "room_sandin_dangerpuzzle-17": "",
    "room_sandin_dangerpuzzle-18": "",
    "room_sandin_dangerpuzzle-19": "",
    "room_sandin_dangerpuzzle-20": "",
    "room_sandin_dangerpuzzle-21": "",
    "room_sandin_dangerpuzzle-22": "",
    "room_sandin_dangerpuzzle-23": "",
    "room_sandin_dangerpuzzle-24": "",
    "room_sandin_dangerpuzzle-25": "",
    "room_sandin_dangerpuzzle-26": "",
    "room_sandin_dangerpuzzle-27": "",
    "room_sandin_dangerpuzzle-28": "",
    "room_tundra-0": "",
    "room_tundra-1": "",
    "room_tundra-2": "",
    "room_tundra-3": "",
    "room_tundra-4": "",
    "room_tundra-5": "",
    "room_tundra-6": "",
    "room_tundra-7": "",
    "room_tundra-8": "",
    "room_tundra-9": "",
    "room_tundra-10": "",
    "room_tundra-11": "",
    "room_tundra-12": "",
    "room_tundra-13": "",
    "room_tundra-14": "",
    "room_tundra-15": "",
    "room_tundra-16": "",
    "room_tundra-17": "",
    "room_tundra-18": "",
    "room_tundra-19": "",
    "room_tundra-20": "",
    "room_tundra-21": "",
    "room_tundra-22": "",
    "room_tundra-23": "",
    "room_tundra-24": "",
    "room_tundra-25": "",
    "room_tundra-26": "",
    "room_tundra-27": "",
    "room_tundra-28": "",
    "room_tundra-29": "",
    "room_tundra2-0": "",
    "room_tundra2-1": "",
    "room_tundra2-2": "",
    "room_tundra2-3": "",
    "room_tundra2-4": "",
    "room_tundra2-5": "",
    "room_tundra_rivermen-0": "",
    "room_tundra_rivermen-1": "",
    "room_tundra_rivermen-2": "",
    "room_tundra_rivermen-3": "",
    "room_tundra_rivermen-4": "",
    "room_tundra_rivermen-5": "",
    "room_tundra_rivermen-6": "",
    "room_tundra_rivermen-7": "",
    "room_tundra_rivermen-8": "",
    "room_tundra_rivermen-9": "",
    "room_tundra_rivermen-10": "",
    "room_tundra_rivermen-11": "",
    "room_tundra_rivermen-12": "",
    "room_tundra_rivermen-13": "",
    "room_tundra_rivermen-14": "",
    "room_tundra_rivermen-15": "",
    "room_tundra_rivermen-16": "",
    "room_tundra_rivermen-17": "",
    "room_tundra_rivermen-18": "",
    "room_tundra_interiors-0": "",
    "room_tundra_interiors-1": "",
    "room_tundra_interiors-2": "",
    "room_tundra_interiors-3": "",
    "room_tundra_interiors-4": "",
    "room_tundra_interiors-5": "",
    "room_tundra_interiors-6": "",
    "room_tundra_interiors-7": "",
    "room_tundra_interiors-8": "",
    "room_tundra_interiors-9": "* 是啊...",
    "room_tundra_interiors-10": "",
    "room_tundra_interiors-11": "",
    "room_tundra_interiors-12": "",
    "room_tundra_interiors-13": "",
    "room_tundra_interiors-14": "",
    "room_tundra_interiors-15": "",
    "room_tundra_interiors-16": "",
    "room_tundra_interiors-17": "",
    "room_tundra_interiors-18": "",
    "room_tundra_interiors-19": "",
    "room_tundra_interiors-20": "",
    "room_tundra_interiors-21": "",
    "room_tundra_interiors-22": "",
    "room_tundra_interiors-23": "",
    "room_tundra_interiors-24": "",
    "room_tundra_interiors-25": "",
    "room_tundra_interiors-26": "",
    "room_tundra_interiors-27": "",
    "room_tundra_interiors-28": "",
    "room_tundra_interiors-29": "",
    "room_tundra_interiors-30": "",
    "room_tundra_interiors-31": "",
    "room_tundra_interiors-32": "",
    "room_tundra_interiors-33": "",
    "room_tundra_interiors-34": "",
    "room_tundra_interiors-35": "",
    "room_tundra_interiors-36": "",
    "room_tundra_interiors-37": "",
    "room_tundra_interiors-38": "",
    "room_tundra_interiors-39": "",
    "room_tundra_interiors-40": "",
    "room_tundra_interiors-41": "",
    "room_tundra_interiors-42": "",
    "room_tundra_interiors-43": "",
    "room_tundra_interiors-44": "",
    "room_tundra_interiors-45": "",
    "room_tundra_interiors-46": "",
    "room_tundra_interiors-47": "",
    "room_tundra_interiors-48": "",
    "room_tundra_interiors-49": "",
    "room_tundra_interiors-50": "",
    "room_tundra_interiors-51": "",
    "room_tundra_interiors-52": "",
    "room_tundra_interiors-53": "",
    "room_tundra_interiors-54": "",
    "room_tundra_interiors-55": "",
    "room_tundra_interiors-56": "",
    "room_tundra_interiors-57": "",
    "room_tundra_interiors-58": "",
    "room_tundra_interiors-59": "",
    "room_tundra_interiors-60": "",
    "room_tundra_interiors-61": "",
    "room_tundra_interiors-62": "",
    "room_tundra_interiors-63": "",
    "room_tundra_interiors-64": "",
    "room_tundra_interiors-65": "",
    "room_tundra_interiors-66": "",
    "room_tundra_interiors-67": "",
    "room_tundra_interiors-68": "",
    "room_tundra_interiors-69": "",
    "room_tundra_interiors-70": "",
    "room_tundra_interiors-71": "",
    "room_tundra_interiors-72": "",
    "room_tundra_interiors-73": "",
    "room_tundra_interiors-74": "",
    "room_tundra_interiors-75": "",
    "room_tundra_interiors-76": "",
    "room_tundra_interiors-77": "",
    "room_tundra_interiors-78": "",
    "room_tundra_interiors-79": "",
    "room_tundra_interiors-80": "",
    "room_tundra_interiors-81": "",
    "room_tundra_interiors-82": "",
    "room_tundra_interiors-83": "",
    "room_tundra_interiors-84": "",
    "room_tundra_interiors-85": "",
    "room_tundra_interiors-86": "",
    "room_tundra_interiors-87": "* 那是什么？",
    "room_tundra_interiors-88": "",
    "room_tundra_interiors-89": "",
    "room_tundra_interiors-90": "",
    "room_tundra_interiors-91": "",
    "room_tundra_interiors-92": "",
    "room_tundra_interiors-93": "",
    "room_tundra_interiors-94": "",
    "room_tundra_interiors-95": "",
    "room_tundra_interiors-96": "",
    "room_tundra_interiors-97": "",
    "room_tundra_interiors-98": "",
    "room_tundra_interiors-99": "",
    "room_tundra_interiors-100": "",
    "room_tundra_interiors-101": "",
    "room_tundra_interiors-102": "",
    "room_tundra_interiors-103": "",
    "room_tundra_interiors-104": "",
    "room_tundra_interiors-105": "",
    "room_tundra_interiors-106": "",
    "room_tundra_interiors-107": "",
    "room_tundra_interiors-108": "",
    "room_tundra_interiors-109": "",
    "room_tundra_interiors-110": "",
    "room_tundra_interiors-111": "",
    "room_tundra_interiors-112": "",
    "room_tundra_interiors-113": "",
    "room_tundra_interiors-114": "",
    "room_tundra_interiors-115": "",
    "room_tundra_interiors-116": "",
    "room_tundra_interiors-117": "",
    "room_tundra_interiors-118": "",
    "room_tundra_interiors-119": "",
    "room_tundra_interiors-120": "",
    "room_tundra_interiors-121": "",
    "room_tundra_interiors-122": "",
    "room_tundra_interiors-123": "",
    "room_tundra_interiors-124": "",
    "room_tundra_interiors-125": "",
    "room_tundra_interiors-126": "",
    "room_tundra_interiors-127": "",
    "room_tundra_interiors-128": "",
    "room_tundra_interiors-129": "",
    "room_tundra_interiors-130": "",
    "room_tundra_interiors-131": "",
    "room_tundra_interiors-132": "",
    "room_tundra_interiors-133": "",
    "room_tundra_interiors-134": "",
    "room_tundra_interiors-135": "",
    "room_tundra_interiors-136": "",
    "room_tundra_interiors-137": "",
    "room_tundra_interiors-138": "",
    "room_tundra_interiors-139": "",
    "room_tundra_interiors-140": "",
    "room_tundra_interiors-141": "",
    "room_tundra_interiors-142": "",
    "room_tundra_interiors-143": "",
    "room_tundra_interiors-144": "",
    "room_tundra_interiors-145": "",
    "room_tundra_interiors-146": "",
    "room_tundra_interiors-147": "",
    "room_tundra_interiors-148": "",
    "room_tundra_interiors-149": "",
    "room_tundra_interiors-150": "",
    "room_tundra_interiors-151": "",
    "room_tundra_interiors-152": "",
    "room_tundra_interiors-153": "",
    "room_tundra_interiors-154": "",
    "room_tundra_interiors-155": "",
    "room_tundra_interiors-156": "",
    "room_tundra_interiors-157": "",
    "room_tundra_interiors-158": "",
    "room_tundra_interiors-159": "",
    "room_tundra_interiors-160": "",
    "room_tundra_interiors-161": "",
    "room_tundra_interiors-162": "",
    "room_tundra_interiors-163": "",
    "room_tundra_interiors-164": "",
    "room_tundra_interiors-165": "",
    "room_tundra_interiors-166": "",
    "room_tundra_interiors-167": "",
    "room_tundra_interiors-168": "",
    "room_tundra_interiors-169": "",
    "room_tundra_interiors-170": "",
    "room_tundra_interiors-171": "",
    "room_tundra_interiors-172": "",
    "room_tundra_interiors-173": "",
    "room_tundra_interiors-174": "",
    "room_tundra_interiors-175": "",
    "room_tundra_interiors-176": "",
    "room_tundra_interiors-177": "",
    "room_tundra_interiors-178": "",
    "room_tundra_interiors-179": "",
    "room_tundra_interiors-180": "",
    "room_tundra_interiors-181": "",
    "room_tundra_interiors-182": "",
    "room_tundra_interiors-183": "",
    "room_tundra_interiors-184": "",
    "room_tundra_interiors-185": "",
    "room_tundra_interiors-186": "",
    "room_tundra_interiors-187": "",
    "room_tundra_interiors-188": "",
    "room_tundra_interiors-189": "",
    "room_tundra_interiors-190": "",
    "room_tundra_interiors-191": "",
    "room_tundra_interiors-192": "",
    "room_tundra_interiors-193": "",
    "room_tundra_interiors-194": "",
    "room_tundra_interiors-195": "",
    "room_tundra_interiors-196": "",
    "room_tundra_interiors-197": "",
    "room_tundra_interiors-198": "",
    "room_tundra_interiors-199": "",
    "room_tundra_interiors-200": "",
    "room_tundra_interiors-201": "",
    "room_tundra_interiors-202": "",
    "room_tundra_interiors-203": "",
    "room_tundra_interiors-204": "",
    "room_tundra_interiors-205": "",
    "room_tundra_interiors-206": "",
    "room_tundra_interiors-207": "",
    "room_tundra_interiors-208": "",
    "room_tundra_interiors-209": "",
    "room_tundra_interiors-210": "",
    "room_tundra_interiors-211": "",
    "room_tundra_interiors-212": "",
    "room_tundra_interiors-213": "",
    "room_tundra_interiors-214": "",
    "room_tundra_interiors-215": "",
    "room_tundra_interiors-216": "",
    "room_tundra_interiors-217": "",
    "room_tundra_interiors-218": "",
    "room_tundra_interiors-219": "",
    "room_tundra_interiors-220": "",
    "room_tundra_interiors-221": "",
    "room_tundra_interiors-222": "",
    "room_tundra_interiors-223": "",
    "room_tundra_interiors-224": "",
    "room_tundra_interiors-225": "",
    "room_tundra_interiors-226": "",
    "room_tundra_interiors-227": "",
    "room_tundra_interiors-228": "",
    "room_tundra_interiors-229": "",
    "room_tundra_interiors-230": "",
    "room_tundra_interiors-231": "",
    "room_tundra_interiors-232": "",
    "room_tundra_interiors-233": "",
    "room_tundra_interiors-234": "",
    "room_tundra_interiors-235": "",
    "room_tundra_interiors-236": "",
    "room_tundra_interiors-237": "",
    "room_tundra_interiors-238": "",
    "room_tundra_interiors-239": "",
    "room_tundra_interiors-240": "",
    "room_tundra_interiors-241": "",
    "room_tundra_interiors-242": "",
    "room_tundra_interiors-243": "",
    "room_tundra_interiors-244": "",
    "room_tundra_interiors-245": "",
    "room_tundra_interiors-246": "",
    "room_tundra_interiors-247": "",
    "room_tundra_interiors-248": "",
    "room_tundra_interiors-249": "",
    "room_tundra_interiors-250": "",
    "room_tundra_interiors-251": "",
    "room_tundra_interiors-252": "",
    "room_tundra_interiors-253": "",
    "room_tundra_interiors-254": "",
    "room_tundra_interiors-255": "",
    "room_tundra_interiors-256": "",
    "room_tundra_interiors-257": "",
    "room_tundra_interiors-258": "",
    "room_tundra_interiors-259": "",
    "room_tundra_interiors-260": "",
    "room_tundra_interiors-261": "",
    "room_tundra_interiors-262": "",
    "room_tundra_interiors-263": "",
    "room_tundra_interiors-264": "",
    "room_tundra_interiors-265": "",
    "room_tundra_interiors-266": "",
    "room_tundra_interiors-267": "",
    "room_tundra_interiors-268": "",
    "room_tundra_interiors-269": "",
    "room_tundra_interiors-270": "",
    "room_tundra_interiors-271": "",
    "room_tundra_interiors-272": "",
    "room_tundra_interiors-273": "",
    "room_tundra_interiors-274": "",
    "room_tundra_interiors-275": "",
    "room_tundra_interiors-276": "",
    "room_tundra_interiors-277": "",
    "room_tundra_interiors-278": "",
    "room_tundra_interiors-279": "",
    "room_tundra_interiors-280": "",
    "room_tundra_interiors-281": "",
    "room_tundra_interiors-282": "",
    "room_tundra_interiors-283": "",
    "room_tundra_interiors-284": "",
    "room_tundra_interiors-285": "",
    "room_tundra_interiors-286": "",
    "room_tundra_interiors-287": "",
    "room_tundra_interiors-288": "",
    "room_tundra_interiors-289": "",
    "room_tundra_interiors-290": "",
    "room_tundra_interiors-291": "",
    "room_tundra_interiors-292": "",
    "room_tundra_interiors-293": "",
    "room_tundra_interiors-294": "",
    "room_tundra_interiors-295": "",
    "room_tundra_interiors-296": "",
    "room_tundra_interiors-297": "",
    "room_ship-0": "",
    "room_ship-1": "",
    "room_ship-2": "",
    "room_ship-3": "",
    "room_ship-4": "",
    "room_ship-5": "",
    "room_ship-6": "",
    "room_ship-7": "",
    "room_ship-8": "",
    "room_ship-9": "",
    "room_ship-10": "",
    "room_ship-11": "",
    "room_ship-12": "",
    "room_ship-13": "",
    "room_ship-14": "",
    "room_ship-15": "",
    "room_ship-16": "",
    "room_ship-17": "",
    "room_ship-18": "",
    "room_ship-19": "",
    "room_ship-20": "",
    "room_ship-21": "",
    "room_ship_interior-0": "",
    "room_ship_interior-1": "",
    "room_ship_interior-2": "",
    "room_ship_interior-3": "",
    "room_ship_interior-4": "",
    "room_ship_interior-5": "",
    "room_ship_interior-6": "",
    "room_ship_interior-7": "",
    "room_ship_interior-8": "",
    "room_ship_interior-9": "",
    "room_ship_interior-10": "",
    "room_ship_interior-11": "",
    "room_ship_interior-12": "",
    "room_ship_interior-13": "",
    "room_ship_interior-14": "",
    "room_ship_interior-15": "",
    "room_ship_interior-16": "",
    "room_ship_interior-17": "",
    "room_ship_interior-18": "",
    "room_ship_interior-19": "",
    "room_ship_interior-20": "",
    "room_ship_interior-21": "",
    "room_ship_interior-22": "",
    "room_ship_interior-23": "",
    "room_ship_interior-24": "",
    "room_ship_interior-25": "",
    "room_ship_interior-26": "",
    "room_ship_interior-27": "",
    "room_ship_interior-28": "",
    "room_ship_interior-29": "",
    "room_ship_interior-30": "",
    "room_ship_interior-31": "",
    "room_ship_interior-32": "",
    "room_ship_interior-33": "",
    "room_ship_interior-34": "",
    "room_ship_interior-35": "",
    "room_ship_interior-36": "",
    "room_ship_interior-37": "",
    "room_ship_interior-38": "",
    "room_ship_interior-39": "",
    "room_ship_interior-40": "",
    "room_ship_interior-41": "",
    "room_ship_interior-42": "",
    "room_ship_interior-43": "",
    "room_ship_interior-44": "",
    "room_ship_interior-45": "",
    "room_ship_interior-46": "",
    "room_ship_interior-47": "",
    "room_ship_interior-48": "",
    "room_ship_interior-49": "",
    "room_ship_interior-50": "",
    "room_ship_interior-51": "",
    "room_ship_interior-52": "",
    "room_ship_interior-53": "",
    "room_ship_interior-54": "",
    "room_ship_interior-55": "",
    "room_ship_interior-56": "",
    "room_ship_interior-57": "",
    "room_ship_interior-58": "",
    "room_ship_interior-59": "",
    "room_ship_interior-60": "",
    "room_ship_interior-61": "",
    "room_ship_interior-62": "",
    "room_ship_interior-63": "",
    "room_ship_interior-64": "",
    "room_ship_interior-65": "",
    "room_ship_interior-66": "",
    "room_ship_interior-67": "",
    "room_cave-0": "",
    "room_cave-1": "",
    "room_cave-2": "",
    "room_cave-3": "",
    "room_cave-4": "",
    "room_cave-5": "",
    "room_cave-6": "",
    "room_cave-7": "",
    "room_cave-8": "",
    "room_cave-9": "",
    "room_cave-10": "",
    "room_cave-11": "",
    "room_cave-12": "",
    "room_cave-13": "",
    "room_cave-14": "",
    "room_cave-15": "",
    "room_cave_seawoods-0": "",
    "room_cave_seawoods-1": "",
    "room_cave_seawoods-2": "",
    "room_cave_seawoods-3": "",
    "room_cave_seawoods-4": "",
    "room_cave_seawoods-5": "",
    "room_cave_seawoods-6": "",
    "room_cave_seawoods-7": "",
    "room_cave_seawoods-8": "",
    "room_cave_seawoods-9": "",
    "room_cave_seawoods-10": "",
    "room_cave_seawoods-11": "",
    "room_cave_seawoods-12": "",
    "room_cave_seawoods-13": "",
    "room_cave_seawoods-14": "",
    "room_cave_seawoods-15": "",
    "room_cave_seawoods-16": "",
    "room_cave_seawoods-17": "",
    "room_cave_seawoods-18": "",
    "room_cave_seawoods-19": "",
    "room_cave_seawoods-20": "",
    "room_cave_seawoods-21": "",
    "room_cave_seawoods-22": "",
    "room_cave_seawoods-23": "",
    "room_cave_seawoods-24": "",
    "room_cave_seawoods-25": "",
    "room_cave_cliffs-0": "",
    "room_cave_cliffs-1": "",
    "room_cave_cliffs-2": "",
    "room_cave_cliffs-3": "",
    "room_cave_cliffs-4": "",
    "room_cave_cliffs-5": "",
    "room_cave_cliffs-6": "",
    "room_cave_cliffs-7": "",
    "room_cave_cliffs-8": "",
    "room_cave_cliffs-9": "",
    "room_cave_cliffs-10": "",
    "room_cave_cliffs-11": "",
    "room_cave_cliffs-12": "",
    "room_cave_cliffs-13": "",
    "room_cave_cliffs-14": "",
    "room_cave_cliffs-15": "",
    "room_cave_cliffs-16": "",
    "room_cave_cliffs-17": "",
    "room_cave_cliffs-18": "",
    "room_cave_cliffs-19": "",
    "room_cave_cliffs-20": "",
    "room_cave_5-0": "",
    "room_cave_5-1": "",
    "room_cave_5-2": "",
    "room_cave_5-3": "",
    "room_cave_5-4": "",
    "room_cave_5-5": "",
    "room_cave_5-6": "",
    "room_cave_5-7": "",
    "room_cave_5-8": "",
    "room_cave_5-9": "",
    "room_cave_5-10": "",
    "room_cave_5-11": "",
    "room_cave_5-12": "",
    "room_cave_5-13": "",
    "room_cave_5-14": "",
    "room_cave_5-15": "",
    "room_cave_5-16": "",
    "room_cave_5-17": "",
    "room_cave_5-18": "",
    "room_cave_5-19": "",
    "room_cave_5-20": "",
    "room_cave_5-21": "",
    "room_cave_7-0": "",
    "room_cave_7-1": "",
    "room_cave_7-2": "",
    "room_cave_7-3": "",
    "room_cave_9-0": "",
    "room_cave_9-1": "",
    "room_cave_9-2": "",
    "room_cave_9-3": "",
    "room_cave_9-4": "",
    "room_cave_9-5": "",
    "room_cave_9-6": "",
    "room_cave_9-7": "",
    "room_cave_9-8": "",
    "room_cave_9-9": "",
    "room_cave_9-10": "",
    "room_cave_9-11": "",
    "room_cave_9-12": "",
    "room_cave_10-0": "",
    "room_cave_10-1": "",
    "room_cave_shopkeeper_taco-0": "",
    "room_cave_shopkeeper_taco-1": "",
    "room_cave_shopkeeper_taco-2": "",
    "room_cave_shopkeeper_taco-3": "",
    "room_cave_shopkeeper_taco-4": "",
    "room_cave_shopkeeper_taco-5": "",
    "room_cave_shopkeeper_taco-6": "",
    "room_cave_shopkeeper_taco-7": "",
    "room_cave_shopkeeper_taco-8": "",
    "room_cave_shopkeeper_taco-9": "",
    "room_cave_shopkeeper_taco-10": "",
    "room_cave_shopkeeper_taco-11": "",
    "room_cave_shopkeeper_taco-12": "",
    "room_cave_shopkeeper_taco-13": "",
    "room_cave_shopkeeper_taco-14": "",
    "room_cave_shopkeeper_taco-15": "",
    "room_cave_shopkeeper_taco-16": "",
    "room_cave_shopkeeper_taco-17": "",
    "room_cave_shopkeeper_taco-18": "",
    "room_cave_shopkeeper_taco-19": "",
    "room_cave_shopkeeper_taco-20": "* 我知道了。",
    "room_cave_shopkeeper_taco-21": "",
    "room_cave_shopkeeper_taco-22": "",
    "room_cave_shopkeeper_taco-23": "",
    "room_cave_shopkeeper_taco-24": "",
    "room_cave_shopkeeper_taco-25": "",
    "room_cave_shopkeeper_taco-26": "",
    "room_cave_shopkeeper_taco-27": "",
    "room_cave_shopkeeper_taco-28": "",
    "room_cave_shopkeeper_taco-29": "",
    "room_cave_shopkeeper_taco-30": "",
    "room_cave_shopkeeper_taco-31": "",
    "room_cave_shopkeeper_taco-32": "",
    "room_cave_shopkeeper_taco-33": "",
    "room_cave_shopkeeper_taco-34": "",
    "room_cave_shopkeeper_taco-35": "",
    "room_cave_shopkeeper_taco-36": "",
    "room_cave_shopkeeper_taco-37": "",
    "room_cave_shopkeeper_taco-38": "",
    "room_cave_shopkeeper_taco-39": "",
    "room_cave_shopkeeper_taco-40": "",
    "room_cave_shopkeeper_taco-41": "",
    "room_cave_shopkeeper_taco-42": "",
    "room_cave_shopkeeper_taco-43": "",
    "room_cave_shopkeeper_taco-44": "",
    "room_cave_shopkeeper_taco-45": "",
    "room_cave_shopkeeper_taco-46": "",
    "room_cave_shopkeeper_taco-47": "",
    "room_cave_shopkeeper_taco-48": "",
    "room_cave_shopkeeper_taco-49": "",
    "room_cave_shopkeeper_taco-50": "",
    "room_cave_shopkeeper_taco-51": "",
    "room_cave_octo-san-0": "",
    "room_cave_octo-san-1": "",
    "room_cave_octo-san-2": "",
    "room_cave_octo-san-3": "",
    "room_cave_octo-san-4": "",
    "room_cave_octo-san-5": "",
    "room_cave_octo-san-6": "",
    "room_cave_octo-san-7": "",
    "room_cave_octo-san-8": "",
    "room_cave_octo-san-9": "",
    "room_cave_octo-san-10": "",
    "room_cave_octo-san-11": "",
    "room_cave_octo-san-12": "",
    "room_cave_octo-san-13": "",
    "room_cave_octo-san-14": "",
    "room_cave_octo-san-15": "",
    "room_cave_octo-san-16": "",
    "room_cave_octo-san-17": "",
    "room_cave_13-0": "",
    "room_cave_13-1": "",
    "room_cave_13-2": "",
    "room_cave_13-3": "",
    "room_cave_13-4": "",
    "room_cave_13-5": "",
    "room_cave_13-6": "",
    "room_cave_13-7": "",
    "room_cave_13-8": "",
    "room_cave_13-9": "",
    "room_cave_13-10": "",
    "room_cave_13-11": "",
    "room_cave_13-12": "",
    "room_cave_13-13": "",
    "room_cave_13-14": "",
    "room_cave_13-15": "",
    "room_cave_13-16": "",
    "room_cave_13-17": "",
    "room_cave_13-18": "",
    "room_cave_13-19": "",
    "room_cave_13-20": "",
    "room_cave_13-21": "",
    "room_cave_13-22": "",
    "room_cave_13-23": "",
    "room_cave_13-24": "",
    "room_cave_13-25": "",
    "room_cave_13-26": "",
    "room_cave_13-27": "",
    "room_cave_13-28": "",
    "room_cave_13-29": "",
    "room_cave_13-30": "",
    "room_cave_13-31": "",
    "room_cave_13-32": "",
    "room_cave_13-33": "",
    "room_cave_13-34": "",
    "room_cave_13-35": "",
    "room_cave_13-36": "",
    "room_cave_13-37": "",
    "room_cave_13-38": "",
    "room_cave_13-39": "",
    "room_cave_13-40": "",
    "room_cave_13-41": "",
    "room_cave_13-42": "",
    "room_cave_13-43": "",
    "room_cave_13-44": "",
    "room_cave_13-45": "",
    "room_cave_13-46": "",
    "room_cave_13-47": "",
    "room_cave_13-48": "",
    "room_cave_13-49": "",
    "room_cave_13-50": "",
    "room_cave_13-51": "",
    "room_cave_13-52": "",
    "room_cave_13-53": "",
    "room_cave_13-54": "",
    "room_cave_13-55": "",
    "room_cave_13-56": "",
    "room_cave_13-57": "",
    "room_cave_13-58": "",
    "room_cave_13-59": "",
    "room_cave_13-60": "",
    "room_cave_13-61": "",
    "room_cave_13-62": "",
    "room_cave_13-63": "",
    "room_cave_13-64": "",
    "room_cave_13-65": "",
    "room_cave_13-66": "",
    "room_cave_13-67": "",
    "room_cave_13-68": "",
    "room_cave_13-69": "",
    "room_cave_13-70": "",
    "room_cave_13-71": "",
    "room_cave_13-72": "",
    "room_cave_13-73": "",
    "room_cave_13-74": "",
    "room_cave_13-75": "",
    "room_cave_13-76": "",
    "room_cave_darkway-0": "",
    "room_cave_darkway-1": "",
    "room_cave_darkway-2": "",
    "room_cave_darkway-3": "",
    "room_cave_darkway-4": "",
    "room_cave_darkway-5": "",
    "room_cave_darkway-6": "",
    "room_cave_darkway-7": "",
    "room_cave_darkway-8": "",
    "room_cave_darkway-9": "",
    "room_cave_darkway-10": "",
    "room_cave_darkway-11": "",
    "room_cave_darkway-12": "",
    "room_cave_darkway-13": "",
    "room_cave_darkway-14": "",
    "room_cave_darkway-15": "",
    "room_cave_darkway-16": "",
    "room_cave_darkway-17": "",
    "room_cave_darkway-18": "",
    "room_cave_darkway-19": "",
    "room_cave_darkway-20": "",
    "room_cave_darkway-21": "",
    "room_cave_darkway-22": "",
    "room_cave_darkway-23": "",
    "room_cave_darkway-24": "",
    "room_cave_darkway-25": "",
    "room_cave_darkway-26": "",
    "room_cave_darkway-27": "",
    "room_cave_darkway-28": "",
    "room_cave_darkway-29": "",
    "room_cave_15-0": "",
    "room_cave_15-1": "",
    "room_cave_15-2": "",
    "room_cave_15-3": "",
    "room_cave_15-4": "",
    "room_cave_15-5": "",
    "room_cave_undynebridge-0": "",
    "room_cave_undynebridge-1": "",
    "room_cave_17-0": "",
    "room_cave_17-1": "",
    "room_cave_17-2": "",
    "room_cave_17-3": "",
    "room_cave_17-4": "",
    "room_cave_17-5": "",
    "room_cave_17-6": "",
    "room_cave_17-7": "",
    "room_cave_17-8": "",
    "room_cave_17-9": "",
    "room_cave_17-10": "",
    "room_cave_17-11": "",
    "room_cave_17-12": "",
    "room_cave_17-13": "",
    "room_cave_enter_gorge-0": "",
    "room_cave_enter_gorge-1": "",
    "room_cave_enter_gorge-2": "",
    "room_cave_enter_gorge-3": "",
    "room_cave_enter_gorge-4": "",
    "room_cave_enter_gorge-5": "",
    "room_cave_enter_gorge-6": "",
    "room_cave_enter_gorge-7": "",
    "room_cave_enter_gorge-8": "",
    "room_cave_enter_gorge-9": "",
    "room_cave_enter_gorge-10": "",
    "room_cave_enter_gorge-11": "",
    "room_cave_enter_gorge-12": "",
    "room_cave_enter_gorge-13": "",
    "room_cave_enter_gorge-14": "",
    "room_cave_enter_gorge-15": "",
    "room_cave_enter_gorge-16": "",
    "room_cave_enter_gorge-17": "",
    "room_cave_enter_gorge-18": "",
    "room_cave_enter_gorge-19": "",
    "room_cave_enter_gorge-20": "",
    "room_cave_enter_gorge-21": "",
    "room_cave_enter_gorge-22": "",
    "room_cave_enter_gorge-23": "",
    "room_cave_enter_gorge-24": "",
    "room_cave_enter_gorge-25": "",
    "room_cave_enter_gorge-26": "",
    "room_cave_enter_gorge-27": "",
    "room_cave_enter_gorge-28": "",
    "room_cave_enter_gorge-29": "",
    "room_cave_enter_gorge-30": "",
    "room_gorge-0": "",
    "room_gorge-1": "",
    "room_gorge2-0": "",
    "room_gorge2-1": "",
    "room_gorge2-2": "",
    "room_gorge2-3": "",
    "room_gorge2-4": "",
    "room_gorge2-5": "",
    "room_gorge2-6": "",
    "room_gorge2-7": "",
    "room_gorge2-8": "",
    "room_gorge2-9": "",
    "room_gorge2-10": "",
    "room_gorge2-11": "",
    "room_gorge2-12": "",
    "room_gorge3-0": "",
    "room_gorge3-1": "",
    "room_gorge3-2": "",
    "room_gorge3-3": "",
    "room_gorge3-4": "",
    "room_gorge3-5": "",
    "room_gorge3-6": "",
    "room_gorge4-0": "",
    "room_gorge5-0": "",
    "room_gorge6-0": "",
    "room_gorge6-1": "",
    "room_gorge6-2": "",
    "room_gorge6-3": "",
    "room_gorge6-4": "",
    "room_gorge6-5": "",
    "room_gorge6-6": "",
    "room_gorge6-7": "",
    "room_gorge6-8": "",
    "room_gorge6-9": "",
    "room_gorge6-10": "",
    "room_gorge6-11": "",
    "room_gorge6-12": "",
    "room_gorge6-13": "",
    "room_gorge6-14": "",
    "room_gorge6-15": "",
    "room_gorge6-16": "",
    "room_gorge7-0": "",
    "room_gorge7-1": "",
    "room_gorge7-2": "",
    "room_gorge7-3": "",
    "room_gorge7-4": "",
    "room_gorge7-5": "",
    "room_gorge7-6": "",
    "room_gorge7-7": "",
    "room_gorge7-8": "",
    "room_gorge7-9": "",
    "room_gorge7-10": "",
    "room_gorge7-11": "",
    "room_gorge7-12": "",
    "room_gorge7-13": "",
    "room_gorge7-14": "",
    "room_gorge7-15": "",
    "room_gorge7-16": "",
    "room_gorge7-17": "",
    "room_gorge7-18": "",
    "room_gorge7-19": "",
    "room_gorge7-20": "",
    "room_gorge7-21": "",
    "room_gorge7-22": "",
    "room_gorge7-23": "",
    "room_gorge7-24": "",
    "room_gorge7-25": "",
    "room_gorge7-26": "",
    "room_gorge7-27": "",
    "room_gorge7-28": "",
    "room_gorge8-0": "",
    "room_gorge8-1": "",
    "room_gorge8-2": "",
    "room_gorge8-3": "",
    "room_gorge8-4": "",
    "room_gorge8-5": "",
    "room_gorge8-6": "",
    "room_gorge8-7": "",
    "room_gorge8-8": "",
    "room_gorge8-9": "",
    "room_gorge8-10": "",
    "room_gorge8-11": "",
    "room_gorge8-12": "",
    "room_gorge8-13": "",
    "room_gorge8-14": "",
    "room_gorge8-15": "",
    "room_gorge8-16": "",
    "room_gorge8-17": "",
    "room_gorge8-18": "",
    "room_gorge8-19": "",
    "room_gorge8-20": "",
    "room_gorge8-21": "",
    "room_gorge8-22": "",
    "room_gorge8-23": "",
    "room_gorge8-24": "",
    "room_gorge8-25": "",
    "room_gorge8-26": "",
    "room_gorge8-27": "",
    "room_gorge8-28": "",
    "room_gorge8-29": "",
    "room_gorge8-30": "",
    "room_gorge8-31": "",
    "room_gorge8-32": "",
    "room_gorge8-33": "",
    "room_gorge8-34": "",
    "room_gorge8-35": "",
    "room_gorge8-36": "",
    "room_gorge8-37": "",
    "room_gorge8-38": "",
    "room_gorge8-39": "",
    "room_gorge8-40": "",
    "room_gorge8-41": "",
    "room_gorge9-0": "",
    "room_gorge9-1": "",
    "room_gorge9-2": "",
    "room_gorge9-3": "",
    "room_gorge9-4": "",
    "room_gorge9-5": "",
    "room_gorge9-6": "",
    "room_gorge9-7": "",
    "room_gorge9A-0": "",
    "room_gorge9A-1": "",
    "room_gorge9A-2": "",
    "room_gorge9A-3": "",
    "room_gorge9A-4": "",
    "room_gorge9A-5": "",
    "room_gorge9A-6": "",
    "room_gorge9A-7": "",
    "room_gorge9A-8": "",
    "room_gorge9A-9": "",
    "room_gorge9A-10": "",
    "room_gorge9A-11": "",
    "room_gorge9A-12": "",
    "room_gorge9A-13": "",
    "room_gorge9A-14": "",
    "room_gorge9A-15": "",
    "room_gorge9A-16": "",
    "room_gorge9A-17": "",
    "room_gorge9A-18": "",
    "room_gorge9A-19": "",
    "room_gorge9A-20": "",
    "room_gorge9A-21": "",
    "room_gorge9A-22": "",
    "room_gorge9A-23": "",
    "room_gorge9A-24": "",
    "room_gorge9A-25": "",
    "room_gorge9A-26": "",
    "room_gorge9A-27": "",
    "room_gorge9A-28": "",
    "room_gorge9A-29": "",
    "room_gorge9A-30": "",
    "room_gorge9A-31": "",
    "room_gorge9A-32": "",
    "room_gorge9A-33": "",
    "room_gorge9A-34": "",
    "room_gorge9A-35": "",
    "room_gorge9A-36": "",
    "room_gorge9A-37": "",
    "room_gorge9A-38": "",
    "room_gorge9A-39": "",
    "room_gorge9A-40": "",
    "room_gorge9A-41": "",
    "room_gorge9A-42": "",
    "room_gorge9A-43": "",
    "room_gorge9A-44": "",
    "room_gorge9A-45": "",
    "room_gorge9A-46": "",
    "room_gorge9A-47": "",
    "room_gorge9A-48": "",
    "room_gorge9A-49": "",
    "room_gorge9A-50": "",
    "room_gorge9A-51": "",
    "room_gorge9A-52": "",
    "room_gorge9A-53": "",
    "room_gorge9A-54": "",
    "room_gorge9A-55": "",
    "room_gorge9A-56": "",
    "room_gorge9A-57": "",
    "room_gorge9A-58": "",
    "room_gorge9A-59": "",
    "room_gorge9A-60": "",
    "room_gorge9A-61": "",
    "room_gorge9A-62": "",
    "room_gorge9A-63": "",
    "room_gorge9A-64": "",
    "room_gorge9A-65": "",
    "room_gorge9A-66": "",
    "room_gorge9A-67": "",
    "room_gorge9A-68": "",
    "room_gorge9A-69": "",
    "room_gorge9A-70": "",
    "room_gorge9A-71": "",
    "room_gorge9A-72": "",
    "room_gorge9A-73": "",
    "room_gorge9A-74": "",
    "room_gorge9A-75": "",
    "room_gorge9A-76": "",
    "room_gorge9A-77": "",
    "room_gorge9A-78": "",
    "room_gorge9A-79": "",
    "room_gorge9A-80": "* 行。",
    "room_gorge9A-81": "",
    "room_gorge9A-82": "",
    "room_gorge9A-83": "",
    "room_gorge9A-84": "",
    "room_gorge9A-85": "",
    "room_gorge9A-86": "",
    "room_gorge9A-87": "* 我知道了。",
    "room_gorge9A-88": "",
    "room_gorge9A-89": "",
    "room_gorge9A-90": "",
    "room_gorge9A-91": "",
    "room_gorge9A-92": "",
    "room_gorge9A-93": "",
    "room_gorge9A-94": "",
    "room_gorge9A-95": "",
    "room_gorge9A-96": "",
    "room_gorge9A-97": "",
    "room_gorge9A-98": "",
    "room_gorge9A-99": "",
    "room_gorge9A-100": "",
    "room_gorge9A-101": "",
    "room_gorge9A-102": "",
    "room_gorge9A-103": "",
    "room_gorge9A-104": "",
    "room_gorge9A-105": "",
    "room_gorge9A-106": "",
    "room_gorge9A-107": "",
    "room_gorge9A-108": "",
    "room_gorge9A-109": "",
    "room_gorge9A-110": "",
    "room_gorge9A-111": "",
    "room_gorge9A-112": "",
    "room_gorge9A-113": "",
    "room_gorge9A-114": "",
    "room_gorge9A-115": "",
    "room_gorge9A-116": "",
    "room_gorge11-0": "",
    "room_gorge11-1": "",
    "room_gorge11-2": "",
    "room_gorge11-3": "",
    "room_gorge11-4": "",
    "room_gorge11-5": "",
    "room_gorge11-6": "",
    "room_gorge11-7": "",
    "room_gorge11-8": "",
    "room_gorge11-9": "",
    "room_gorge11-10": "",
    "room_gorge11-11": "",
    "room_gorge11-12": "",
    "room_gorge11-13": "",
    "room_gorge11-14": "",
    "room_gorge11-15": "",
    "room_gorge11-16": "",
    "room_gorge11-17": "",
    "room_gorge_tem-0": "",
    "room_gorge_tem-1": "",
    "room_gorge_tem-2": "",
    "room_gorge_tem-3": "",
    "room_gorge_tem-4": "",
    "room_gorge_tem-5": "",
    "room_gorge_tem-6": "",
    "room_gorge_tem-7": "",
    "room_gorge_tem-8": "",
    "room_gorge_tem-9": "",
    "room_gorge_tem-10": "",
    "room_gorge_tem-11": "",
    "room_gorge_tem-12": "",
    "room_gorge_tem-13": "",
    "room_gorge_tem-14": "",
    "room_gorge_tem-15": "",
    "room_gorge_tem-16": "",
    "room_gorge_tem-17": "",
    "room_gorge_tem-18": "",
    "room_gorge_tem-19": "",
    "room_gorge_tem-20": "",
    "room_gorge_tem-21": "",
    "room_gorge_tem-22": "",
    "room_gorge_tem-23": "",
    "room_gorge_tem-24": "",
    "room_gorge_tem-25": "",
    "room_gorge_tem-26": "",
    "room_gorge_tem-27": "",
    "room_gorge_tem-28": "",
    "room_gorge_tem-29": "",
    "room_gorge_tem-30": "",
    "room_gorge_tem-31": "",
    "room_gorge_tem-32": "",
    "room_gorge_tem-33": "",
    "room_gorge_tem-34": "",
    "room_gorge_tem-35": "",
    "room_gorge_tem-36": "",
    "room_gorge_tem-37": "",
    "room_gorge_tem-38": "",
    "room_gorge_tem-39": "",
    "room_gorge_tem-40": "",
    "room_gorge_tem-41": "",
    "room_gorge_tem-42": "",
    "room_gorge_tem-43": "",
    "room_gorge_tem-44": "",
    "room_gorge_tem-45": "",
    "room_gorge_tem-46": "",
    "room_gorge_tem-47": "",
    "room_gorge_tem-48": "",
    "room_gorge_tem-49": "",
    "room_gorge14-0": "",
    "room_gorge14-1": "",
    "room_gorge14-2": "",
    "room_gorge14-3": "",
    "room_gorge14-4": "",
    "room_gorge14-5": "",
    "room_gorge14-6": "",
    "room_gorge14-7": "",
    "room_gorge14-8": "",
    "room_gorge14-9": "",
    "room_gorge14-10": "",
    "room_gorge14-11": "",
    "room_gorge14-12": "",
    "room_gorge14-13": "",
    "room_gorge14-14": "",
    "room_gorge14-15": "",
    "room_gorge14-16": "",
    "room_gorge14-17": "",
    "room_gorge14-18": "",
    "room_gorge15-0": "",
    "room_gorge15-1": "",
    "room_gorge15-2": "",
    "room_gorge15-3": "",
    "room_gorge15-4": "",
    "room_gorge15-5": "",
    "room_gorge15-6": "",
    "room_gorge16-0": "",
    "room_gorge16-1": "",
    "room_gorge16-2": "",
    "room_gorge16-3": "",
    "room_gorge16-4": "",
    "room_gorge16-5": "",
    "room_gorge16-6": "",
    "room_gorge16-7": "",
    "room_gorge16-8": "",
    "room_gorge16-9": "",
    "room_gorge16-10": "",
    "room_gorge16-11": "",
    "room_gorge16-12": "",
    "room_gorge16-13": "",
    "room_gorge16-14": "",
    "room_gorge16-15": "",
    "room_gorge16-16": "",
    "room_gorge16-17": "",
    "room_gorge16-18": "",
    "room_gorge16-19": "",
    "room_gorge16-20": "",
    "room_gorge16-21": "",
    "room_gorge16-22": "",
    "room_gorge16-23": "",
    "room_gorge16-24": "",
    "room_gorge16-25": "",
    "room_gorge16-26": "",
    "room_gorge16-27": "",
    "room_gorge16-28": "",
    "room_gorge16-29": "",
    "room_gorge16-30": "",
    "room_gorge16-31": "",
    "room_gorge16-32": "",
    "room_gorge16-33": "",
    "room_gorge16-34": "",
    "room_gorge16-35": "",
    "room_gorge16-36": "",
    "room_gorge16-37": "",
    "room_gorge16A-0": "",
    "room_gorge16B-0": "",
    "room_gorge16B-1": "",
    "room_gorge16B-2": "",
    "room_gorge16B-3": "",
    "room_gorge16B-4": "",
    "room_gorge16B-5": "",
    "room_gorge16B-6": "",
    "room_gorge16B-7": "",
    "room_gorge16B-8": "",
    "room_gorge16B-9": "",
    "room_gorge16B-10": "",
    "room_gorge16B-11": "",
    "room_gorge16B-12": "",
    "room_gorge16B-13": "",
    "room_gorge16B-14": "",
    "room_gorge16B-15": "",
    "room_gorge16B-16": "",
    "room_gorge16B-17": "",
    "room_gorge16B-18": "",
    "room_gorge16B-19": "",
    "room_gorge16B-20": "",
    "room_gorge16B-21": "",
    "room_gorge16B-22": "",
    "room_gorge16B-23": "",
    "room_gorge16B-24": "",
    "room_gorge16B-25": "",
    "room_gorge16B-26": "",
    "room_gorge16B-27": "",
    "room_gorge16B-28": "",
    "room_ghosthouses-0": "",
    "room_ghosthouses-1": "",
    "room_ghosthouses-2": "",
    "room_ghosthouses-3": "",
    "room_ghosthouses-4": "",
    "room_ghosthouses-5": "",
    "room_ghosthouses-6": "",
    "room_ghosthouses-7": "",
    "room_ghosthouses-8": "",
    "room_ghosthouses-9": "",
    "room_ghosthouses-10": "",
    "room_ghosthouses-11": "",
    "room_ghosthouses-12": "",
    "room_ghosthouses-13": "",
    "room_ghosthouses-14": "",
    "room_ghosthouses-15": "",
    "room_ghosthouses-16": "",
    "room_ghosthouses-17": "",
    "room_ghosthouses-18": "",
    "room_ghosthouses-19": "",
    "room_ghosthouses-20": "",
    "room_ghosthouses-21": "",
    "room_ghosthouses-22": "",
    "room_ghosthouses-23": "",
    "room_ghosthouses-24": "",
    "room_ghosthouses-25": "",
    "room_ghosthouses-26": "",
    "room_ghosthouses-27": "",
    "room_ghosthouses-28": "",
    "room_ghosthouses-29": "",
    "room_ghosthouses-30": "",
    "room_ghosthouses-31": "",
    "room_ghosthouses-32": "",
    "room_ghosthouses-33": "",
    "room_ghosthouses-34": "",
    "room_ghosthouses-35": "",
    "room_ghosthouses-36": "",
    "room_ghosthouses-37": "",
    "room_ghosthouses-38": "",
    "room_ghosthouses-39": "",
    "room_ghosthouses-40": "",
    "room_ghosthouses-41": "",
    "room_ghosthouses-42": "",
    "room_ghosthouses-43": "",
    "room_ghosthouses-44": "",
    "room_ghosthouses-45": "",
    "room_ghosthouses-46": "",
    "room_ghosthouses-47": "",
    "room_ghosthouses-48": "",
    "room_ghosthouses-49": "",
    "room_ghosthouses-50": "",
    "room_gorge17-0": "",
    "room_gorge17-1": "",
    "room_gorge17-2": "",
    "room_gorge17-3": "",
    "room_gorge18-0": "",
    "room_gorge18-1": "",
    "room_gorge18-2": "",
    "room_gorge18-3": "",
    "room_gorge18-4": "",
    "room_gorge18-5": "",
    "room_gorge18-6": "",
    "room_gorge18-7": "",
    "room_gorge18-8": "",
    "room_gorge18-9": "",
    "room_gorge18-10": "",
    "room_gorge18-11": "",
    "room_gorge18-12": "",
    "room_gorge18-13": "",
    "room_gorge18-14": "",
    "room_gorge18-15": "",
    "room_gorge18-16": "",
    "room_gorge18-17": "",
    "room_gorge18-18": "",
    "room_gorge18-19": "",
    "room_gorge18-20": "",
    "room_gorge18-21": "",
    "room_gorge18-22": "",
    "room_gorge18-23": "",
    "room_gorge18-24": "",
    "room_gorge18-25": "",
    "room_gorge18-26": "",
    "room_gorge18-27": "",
    "room_gorge18-28": "",
    "room_gorge18-29": "",
    "room_gorge18-30": "",
    "room_gorge18-31": "",
    "room_gorge18-32": "",
    "room_gorge18-33": "",
    "room_gorge18-34": "",
    "room_gorge18-35": "",
    "room_gorge18-36": "",
    "room_gorge18-37": "",
    "room_gorge18-38": "",
    "room_gorge18-39": "",
    "room_gorge18-40": "",
    "room_gorge18-41": "",
    "room_gorge18-42": "",
    "room_gorge18-43": "",
    "room_gorge18-44": "",
    "room_gorge18-45": "",
    "room_gorge18-46": "",
    "room_gorge18-47": "",
    "room_gorge18-48": "",
    "room_gorge18-49": "",
    "room_gorge18-50": "",
    "room_gorge18-51": "",
    "room_gorge18-52": "",
    "room_gorge18-53": "",
    "room_gorge18-54": "",
    "room_gorge18-55": "",
    "room_gorge18-56": "",
    "room_gorge18-57": "",
    "room_gorge18-58": "",
    "room_hotwater2-0": "",
    "room_hotwater2-1": "",
    "room_hotwater3-0": "",
    "room_hotwater3-1": "",
    "room_hotwater3-2": "",
    "room_hotwater3-3": "",
    "room_hotwater3-4": "",
    "room_hotwater3-5": "",
    "room_hotwater3-6": "",
    "room_hotwater3-7": "",
    "room_hotwater3-8": "",
    "room_hotwater3-9": "",
    "room_hotwater3-10": "",
    "room_hotwater3-11": "",
    "room_hotwater3-12": "",
    "room_chessmaster-0": "",
    "room_chessmaster-1": "",
    "room_chessmaster-2": "",
    "room_chessmaster-3": "",
    "room_chessmaster-4": "",
    "room_chessmaster-5": "",
    "room_chessmaster-6": "",
    "room_chessmaster-7": "",
    "room_chessmaster-8": "",
    "room_chessmaster-9": "",
    "room_chessmaster-10": "",
    "room_gasterlab-0": ""
}
