{
  "page_1.png-底部文本框有头像非战斗": "* Houw\ndy, kid?",
  "page_2.png-底部文本框有头像非战斗": "* You see those cracks?",
  "page_3.png-底部文本框有头像非战斗": "* lell, don’t worry\nabout *em.",
  "page_5.png-底部文本框有头像非战斗": "* See?\n* That's one less\npuzzle to worry about.",
  "page_6.png-底部文本框有头像非战斗": "* Are you gonna do this\nwith all the puzzles?",
  "page_7.png-底部文本框有头像非战斗": "* Just the stupid ones.",
  "page_8.png-底部文本框有头像非战斗": "* What's wrong with\na little teamwork?",
  "page_9.png-底部文本框有头像非战斗": "* Hothing, but I don’t\nwant you to do\nEVYERYTHIHG for me.",
  "page_10.png-底部文本框有头像非战斗": "* I'd never dream of\nit, kiddo...",
  "page_14.png-底部文本框无头像非战斗": "* Dialing...",
  "page_15.png-底部文本框有头像非战斗": "* Howdy?\n* ASGORE here.",
  "page_16.png-底部文本框有头像非战斗": "* Hey, is everything\nokay?",
  "page_17.png-底部文本框有头像非战斗": "* A bit messy, but\nI'11 survive.",
  "page_18.png-底部文本框有头像非战斗": "* And what about you?",
  "page_19.png-底部文本框有头像非战斗": "* I'm good?\n* Just thought I'd say hi.",
  "page_20.png-底部文本框无头像非战斗": "* Click. ..",
  "page_22.png-底部文本框有头像非战斗": "* Howdy?",
  "page_23.png-底部文本框有头像非战斗": "* OQut of curiousity,\nwhich tea do you\nprefer?",
  "page_24.png-底部文本框有头像非战斗": "* Golden flower or\njasmine?\n¥ 6. Flower Jasmine",
  "page_25.png-底部文本框有头像非战斗": "* Golden flower or\njasmine?\nG. Flower ¥ Jasmine",
  "page_26.png-底部文本框有头像非战斗": "* fAh, all right?\n* I'11 try to keep that\nin mind.",
  "page_27.png-底部文本框无头像非战斗": "* Click. ..",
  "page_28.png-底部文本框有头像非战斗": "* ¥ know, you don’t\nhave to lie for my\nsake.",
  "page_29.png-底部文本框有头像非战斗": "* But that’'s like asking\nme to drink “Flowey\ntea. ”",
  "page_31.png-底部文本框有头像非战斗": "* I don’t suppose you'd\nconsider trying other\ntea blends?",
  "page_32.png-底部文本框有头像非战斗": "* Hypothetically speaking.",
  "page_33.png-底部文本框有头像非战斗": "#* Haw, I'm not that\npicky.",
  "page_34.png-底部文本框有头像非战斗": "* 0Oh, good?\n* Hot that I was\nworried. ..",
  "page_35.png-底部文本框有头像非战斗": "* In any case, I'1l see\nyou soon.",
  "page_36.png-底部文本框无头像非战斗": "* Click. ..",
  "page_37.png-底部文本框无头像非战斗": "* Please be gentle when\npushing rocks.\n* They have feelings, too.",
  "page_40.png-底部文本框有头像非战斗": "* Great.\n* Here comes the big\none. ..",
  "page_41.png-底部文本框有头像非战斗": "* Listen, kid.\n* I want you to fall\nthrough the floor.",
  "page_42.png-底部文本框有头像非战斗": "* Are you serious?",
  "page_43.png-底部文本框有头像非战斗": "** Trust me, it's\nperfectly safe.",
  "page_44.png-底部文本框有头像非战斗": "* Asgore made sure\nof that.",
  "page_47.png-底部文本框无头像非战斗": "* 0-oh not\n* I didn’t think you’d come\nover here.",
  "page_48.png-底部文本框无头像非战斗": "* What am I supposed to do?\n* What am I supposed to say?\n* I can’t...",
  "page_49.png-底部文本框有头像非战斗": "st can’ t!",
  "page_51.png-底部文本框有头像非战斗": "* See?\n* He even left some\npillows for ya.",
  "page_52.png-底部文本框有头像非战斗": "* And thanks to this\nvine, you won’t have to\nremember the patternt",
  "page_53.png-底部文本框有头像非战斗": "* But isn’t that\ncheating?",
  "page_54.png-底部文本框有头像非战斗": "* Just think of it as\na shortecut. ..",
  "page_55.png-底部文本框有头像非战斗": "* Remember, the fate\nof the underground\ndepends on us?",
  "page_56.png-底部文本框有头像非战斗": "* Isn’t freedom worth\ncutting a few corners?",
  "page_57.png-底部文本框有头像非战斗": "* Yeah.\n* I can’t argue that.",
  "page_61.png-底部文本框无头像非战斗": "* Dialing...",
  "page_62.png-底部文本框有头像非战斗": "* 0Oh, hello again?",
  "page_63.png-底部文本框有头像非战斗": "* How can I help you?",
  "page_64.png-底部文本框有头像非战斗": "* Well, I just realized.\n* I still don’ t know\nmuch about you.",
  "page_65.png-底部文本框有头像非战斗": "* Hmm. . .\n#* Well, let’'s see...",
  "page_66.png-底部文本框有头像非战斗": "* I have a certain\nfondness for tea\nparties. ..",
  "page_67.png-底部文本框有头像非战斗": "* And lately, I've\ngained a greater\napprecation for puzzles.",
  "page_68.png-底部文本框有头像非战斗": "* But how' d you end\nup here?",
  "page_70.png-底部文本框有头像非战斗": "* That, I'm afraid, is\na story best saved\nfor another day.",
  "page_71.png-底部文本框有头像非战斗": "* But it’s all right?\n* I've grown fond of\nthese RUIHS...",
  "page_72.png-底部文本框有头像非战斗": "* Just give them time,\nand I'm sure you' 11\nfeel right at home.",
  "page_73.png-底部文本框无头像非战斗": "* Click. ..",
  "page_75.png-底部文本框有头像非战斗": "* 50, you gonna do THIS\npuzzle, too?",
  "page_76.png-底部文本框有头像非战斗": "* Hope.\n* It's all yours...",
  "page_77.png-底部文本框有头像非战斗": "* (0f course he’'d leave\nthe easy ones...)",
  "page_78.png-底部文本框有头像非战斗": "* (Well, at least I get\nto do SOMETHIHG on\nny own...J»",
  "page_79.png-顶部文本框无头像非战斗": "* WHOA there, pardner?\n* Who said you could push\nme around?",
  "page_80.png-顶部文本框有头像非战斗": "* (0f all the places\nto start...)",
  "page_83.png-底部文本框有头像非战斗": "* You know, you could\nhave warned me about\nthe talking rock",
  "page_84.png-底部文本框有头像非战斗": "* But I thought you\nwanted to solve the\npuzzles. ..",
  "page_85.png-底部文本框有头像非战斗": "* Hot if it means\nrunning in ecircles...",
  "page_86.png-底部文本框有头像非战斗": "* Hey, you didn’t even\npush all the rocks.",
  "page_87.png-底部文本框有头像非战斗": "* Well, I just had a\nhunch, y’ know.",
  "page_88.png-底部文本框有头像非战斗": "* Does that sound\nweird to you?",
  "page_89.png-底部文本框有头像非战斗": "* Here in the Underground,\nwe call that beginner’s\nluck.",
  "page_92.png-底部文本框无头像非战斗": "* Dialing...",
  "page_93.png-底部文本框有头像非战斗": "* Hey there, Asgorgeous.",
  "page_94.png-底部文本框有头像非战斗": "* Has anyone ever told\nyou that you' re hotter\nthan a cup of tea?",
  "page_96.png-底部文本框有头像非战斗": "* Hoho. ..\n* This is unexpected?",
  "page_97.png-底部文本框有头像非战斗": "#* It’s not that I don’t\nappreciate it, but I'd\nrather just be pals.",
  "page_98.png-底部文本框有头像非战斗": "* Besides, there are\nothers more deserving\nof your... interest.",
  "page_99.png-底部文本框有头像非战斗": "* And you're so young?\n* You have plenty of\ntime to find love.",
  "page_100.png-底部文本框有头像非战斗": "* Don’ t make me take\nthat phone away.",
  "page_101.png-底部文本框无头像非战斗": "* Click. ..",
  "page_103.png-顶部文本框无头像非战斗": "* Look at all the cheese!?\n* 0ddly, one piece is stuck to\nthe table.",
  "page_104.png-顶部文本框无头像非战斗": "* Qut of the kindness in your\nheart, you decide not to\nnibble.",
  "page_105.png-顶部文本框有头像非战斗": "* Hmm. . .\n* I guess I should...",
  "page_106.png-顶部文本框有头像非战斗": "* You got something on\nyour mind?",
  "page_107.png-顶部文本框有头像非战斗": "* ...Hothing serious.\n* We should get going,\nanyway.",
  "page_108.png-顶部文本框有头像非战斗": "* Sure, but don’t forget\nto hit that yellow\nthing.",
  "page_109.png-顶部文本框有头像非战斗": "* 50 you DO know what\nit is?",
  "page_110.png-顶部文本框有头像非战斗": "* Maaaybe.\n* But you’'re the one\nwho keeps touching ’emn.",
  "page_111.png-顶部文本框有头像非战斗": "* Just another “lucky\nguess. ”",
  "page_112.png-顶部文本框无头像非战斗": "* (Knowing that the mouse has so\nmuch cheese to enjoy fills\nyou with determination.)",
  "page_116.png-底部文本框无头像非战斗": "* Geh heh heh...\n* Perfect.",
  "page_117.png-底部文本框无头像非战斗": "* How you’ re TOTALLY\nintimidating.\n* Really.",
  "page_118.png-底部文本框无头像非战斗": "* ASSIMILATION COMPLETE?\n* WE ARE LEGIOH?",
  "page_119.png-底部文本框有头像非战斗": "#* Um, exXcuse me...",
  "page_120.png-底部文本框无头像非战斗": "* INTRUDER???",
  "page_121.png-底部文本框无头像非战斗": "#* Heh, heh, heh...\n* A human, eh?\n* Boy are YOU unlucky...",
  "page_122.png-底部文本框有头像非战斗": "* lWait, I don’t wanna\nfight?!",
  "page_123.png-底部文本框无头像非战斗": "* Buddy, pal, chum, broski...\n* I'm afraid you’ ve got no\nchoice.",
  "page_124.png-底部文本框无头像非战斗": "* YES?\n* ATTACK?\n* FOR THE GLORY OF THE SUWARM?",
  "page_126.png-战斗文本框无头像战斗": "* Loox\n¥ * Dummy\n* Migosp",
  "page_127.png-战斗文本框无头像战斗": "¥ * Check * Talk\n* Hug",
  "page_128.png-战斗文本框无头像战斗": "* DUMMY - ATK 5 DEF &\n* Dressed to look edgy, but still\na softy at heart.",
  "page_131.png-战斗文本框无头像战斗": "* Loox flexes its tiny arms.\n* Ho one is impressed.",
  "page_132.png-战斗文本框无头像战斗": "¥ * Loox\n* Dummy\n* Migosp",
  "page_133.png-战斗文本框无头像战斗": "¥ * Check * Pick On\n* Don’ t Pick On",
  "page_134.png-战斗文本框无头像战斗": "* LO0X - ATK 6 DEF 6\n* Don’t pick on him.\n* Family name: Eyewalker",
  "page_137.png-战斗文本框无头像战斗": "* Cotton puffs fill the air.",
  "page_139.png-战斗文本框无头像战斗": "* It'd be funnier if it didn't\nhurt so much.",
  "page_140.png-战斗文本框无头像战斗": "* Loox\n* Dummy\n¥ * Migosp",
  "page_141.png-战斗文本框无头像战斗": "¥ * Check * Talk",
  "page_142.png-战斗文本框无头像战斗": "* Check W * Talk",
  "page_143.png-战斗文本框无头像战斗": "¥ * Check * Talk",
  "page_144.png-战斗文本框无头像战斗": "* Check W * Talk",
  "page_146.png-战斗文本框无头像战斗": "* Check W * Talk",
  "page_147.png-战斗文本框无头像战斗": "* You try to reason with Migosp,\nbut it won’t listen.",
  "page_150.png-战斗文本框无头像战斗": "* Will this madness ever end?\n* Perhaps there’s an easier\nsolution.",
  "page_151.png-战斗文本框无头像战斗": "¥ * Spare"
}